Workbook
Name FX: 'Assumptions'!$B$5
Name DAYS_PM: 'Assumptions'!$B$6
Name RES_SPEED: 'Assumptions'!$B$7
Name MORT_SPEED: 'Assumptions'!$B$8
Name RES_DELAY: 'Assumptions'!$B$9
Name SAAS_ON: 'Assumptions'!$B$10
Name HOME_M1: 'Assumptions'!$B$14
Name HOME_V1: 'Assumptions'!$C$14
Name HOME_M2: 'Assumptions'!$D$14
Name HOME_V2: 'Assumptions'!$E$14
Name HOME_M3: 'Assumptions'!$F$14
Name HOME_V3: 'Assumptions'!$G$14
Name HOME_ARPU: 'Assumptions'!$B$15
Name HOME_DIRECT: 'Assumptions'!$B$16
Name CONC_M1: 'Assumptions'!$B$17
Name CONC_V1: 'Assumptions'!$C$17
Name CONC_M2: 'Assumptions'!$D$17
Name CONC_V2: 'Assumptions'!$E$17
Name CONC_M3: 'Assumptions'!$F$17
Name CONC_V3: 'Assumptions'!$G$17
Name CONC_FEE: 'Assumptions'!$B$18
Name CONC_DIRECT: 'Assumptions'!$B$19
Name CONS_M1: 'Assumptions'!$B$20
Name CONS_V1: 'Assumptions'!$C$20
Name CONS_M2: 'Assumptions'!$D$20
Name CONS_V2: 'Assumptions'!$E$20
Name CONS_M3: 'Assumptions'!$F$20
Name CONS_V3: 'Assumptions'!$G$20
Name CONS_FEE: 'Assumptions'!$B$21
Name CONS_DIRECT: 'Assumptions'!$B$22
Name REHAB_M1: 'Assumptions'!$B$23
Name REHAB_V1: 'Assumptions'!$C$23
Name REHAB_M2: 'Assumptions'!$D$23
Name REHAB_V2: 'Assumptions'!$E$23
Name REHAB_M3: 'Assumptions'!$F$23
Name REHAB_V3: 'Assumptions'!$G$23
Name REHAB_FEE: 'Assumptions'!$B$24
Name REHAB_DIRECT: 'Assumptions'!$B$25
Name PALLH_M1: 'Assumptions'!$B$26
Name PALLH_V1: 'Assumptions'!$C$26
Name PALLH_M2: 'Assumptions'!$D$26
Name PALLH_V2: 'Assumptions'!$E$26
Name PALLH_M3: 'Assumptions'!$F$26
Name PALLH_V3: 'Assumptions'!$G$26
Name PALLH_FEE: 'Assumptions'!$B$27
Name PALLH_DIRECT: 'Assumptions'!$B$28
Name RES1_OPEN: 'Assumptions'!$B$31
Name RES2_OPEN: 'Assumptions'!$B$32
Name RES1_EFF: 'Assumptions'!$B$33
Name RES2_EFF: 'Assumptions'!$B$34
Name RES_BEDS: 'Assumptions'!$B$35
Name STEP_BEDS: 'Assumptions'!$B$36
Name PALL_BEDS: 'Assumptions'!$B$37
Name RES_OPEN_OCC: 'Assumptions'!$B$38
Name RES_STEP: 'Assumptions'!$B$39
Name RES_CAP: 'Assumptions'!$B$40
Name STEP_OPEN_OCC: 'Assumptions'!$B$41
Name STEP_STEP: 'Assumptions'!$B$42
Name STEP_CAP: 'Assumptions'!$B$43
Name PALL_OPEN_OCC: 'Assumptions'!$B$44

Sheet Cover
A1: Ilé: five-year financial model
A2: October 2026. Confidential. Contact: kemotoks@hotmail.com
A4: Headline
A5: Year-five revenue | B5: =Y5_REV
A6: Year-five EBITDA | B6: =Y5_EBITDA
A7: Year-five EBITDA margin | B7: =IF(Y5_REV=0,0,Y5_EBITDA/Y5_REV)
A8: Peak funding need | B8: =PEAK
A9: Month cash is lowest | B9: =TROUGH_M
A10: EBITDA positive from | B10: =EBITDA_POS
A11: Raise | B11: =RAISE_USD
A12: Raise in naira | B12: =RAISE_NGN
A13: Lowest cash balance after the raise | B13: =MINBAL
A16: How the model is built
A17: Assumptions | B17: Every input, named and blue, with its source. Yellow cells are scenario levers.
A18: Volumes | B18: Clients, members, beds, bodies, cases and licences by month.
A19: Revenue | B19: Twelve streams in four business lines: care in the home, residential care, mortuary and pathology, software.
A20: Costs | B20: Four buckets: direct by stream, site operating, leases, central overhead.
A21: P&L | B21: Revenue by line less the four cost buckets gives EBITDA.
A22: Cash Flow | B22: EBITDA, leases paid a year ahead, capital spend, deposits, the raise, cumulative cash.
A23: Annual | B23: Five-year summary; every figure sums the monthly sheets.
A24: Unit Economics | B24: Per member, client, package, residence and mortuary at steady state.
A25: Market | B25: Bottom-up Lagos sizing with checks against England and the US.
A26: Returns | B26: The round, and the investor's stake at six, eight and ten times EBITDA.
A27: Scenarios | B27: Recorded stress cases, and the live result at the current levers.
A30: Colour code
A31: Blue text: input
A32: Black text: formula
A33: Green text: link to another sheet
A34: Yellow fill: scenario lever
A36: Before tax and depreciation. Figures in naira unless marked; ₦1,500 to the dollar. Ilé is a working name.

Sheet Assumptions
A1: Ilé: assumptions
A2: Blue = input you can change. Every formula in the workbook reads these named cells. Yellow = scenario lever.
A4: 0. Model and scenario levers
A5: Naira per US dollar | B5: 1500 | C5: ₦/$ | H5: Flat over five years; families abroad pay in dollars or pounds
A6: Days in a month | B6: 30.4 | C6: days
A7: Residence fill speed | B7: 1 | C7: x base | H7: 1 = base case; 0.5 = half speed (applies to all three wings)
A8: Mortuary fill speed | B8: 1 | C8: x base | H8: 1 = base case; 0.5 = half speed
A9: Residence delay | B9: 0 | C9: months | H9: Months both residences open late
A10: Software licences sold | B10: 1 | C10: 1 or 0 | H10: 0 = no software revenue
A12: 1. Care in the home
B13: Month 1 | C13: Value 1 | D13: Month 2 | E13: Value 2 | F13: Month 3 | G13: Value 3
A14: Care at home clients (ramp) | B14: 2 | C14: 4 | D14: 18 | E14: 60 | F14: 60 | G14: 110 | H14: Clients on subscription; linear between points, flat after
A15: Care at home revenue per client | B15: 420000 | C15: ₦/month | H15: Blended subscription; Lagos agencies charge ₦119k to ₦359k for carer and nurse packages
A16: Care at home direct cost | B16: 0.6 | C16: of revenue | H16: Carer pay, travel, consumables
A17: Concierge members (ramp) | B17: 3 | C17: 3 | D17: 24 | E17: 30 | F17: 60 | G17: 60
A18: Concierge fee | B18: 650000 | C18: ₦/month | H18: Named doctor and care manager, 24-hour line, hospital visits
A19: Concierge direct cost | B19: 0.5 | C19: of revenue
A20: Virtual consultations a month (ramp) | B20: 2 | C20: 30 | D20: 36 | E20: 250 | F20: 60 | G20: 350
A21: Consultation fee | B21: 30000 | C21: ₦ each
A22: Consultation direct cost | B22: 0.45 | C22: of revenue
A23: Post-operative rehab packages a month (ramp) | B23: 4 | C23: 2 | D23: 36 | E23: 10 | F23: 60 | G23: 15
A24: Rehab package fee | B24: 1200000 | C24: ₦ per six weeks
A25: Rehab direct cost | B25: 0.55 | C25: of revenue
A26: Palliative patients at home (ramp) | B26: 6 | C26: 2 | D26: 24 | E26: 15 | F26: 60 | G26: 25
A27: Palliative at home fee | B27: 900000 | C27: ₦/month
A28: Palliative at home direct cost | B28: 0.65 | C28: of revenue
A30: 2. Residential care (per residence)
A31: Residence one opens | B31: 15 | C31: month | H31: Month 15 = January 2028
A32: Residence two opens | B32: 43 | C32: month | H32: Month 43 = May 2030; paid for from cash flow
A33: Residence one opens, after any delay | B33: =RES1_OPEN+RES_DELAY
A34: Residence two opens, after any delay | B34: =RES2_OPEN+RES_DELAY
A35: Long-stay beds | B35: 12 | C35: beds | H35: 20 beds in all: 12 long-stay, 4 step-down, 4 palliative
A36: Step-down and rehab beds | B36: 4 | C36: beds
A37: Palliative beds | B37: 4 | C37: beds
A38: Long-stay occupied at opening | B38: 5 | C38: beds | H38: Reserved by deposit before opening
A39: Long-stay beds added a month | B39: 0.8 | C39: beds
A40: Long-stay occupancy ceiling | B40: 11 | C40: beds | H40: 11 of 12, 92%
A41: Step-down occupied at opening | B41: 1 | C41: beds
A42: Step-down beds added a month | B42: 0.25 | C42: beds
A43: Step-down occupancy ceiling | B43: 3 | C43: beds
A44: Palliative occupied at opening | B44: 1 | C44: beds
A45: Palliative beds added a month | B45: 0.3 | C45: beds
A46: Palliative occupancy ceiling | B46: 3 | C46: beds
A47: Long-stay fee | B47: 1600000 | C47: ₦/month | H47: About $1,070; Lagos homes publish ₦79k to ₦249k without night nursing
A48: Step-down day rate | B48: 85000 | C48: ₦/day | H48: Nursing and daily physiotherapy
A49: Step-down average stay | B49: 21 | C49: days
A50: Palliative wing fee | B50: 2400000 | C50: ₦/month
A51: Staffing, loaded | B51: 13000000 | C51: ₦/month | H51: Nurses on every shift, care assistants, manager, therapy; includes on-costs
A52: Pre-opening staffing | B52: 0.6 | C52: of staffing | H52: Charged in each of the two months before opening
A53: Food, consumables, laundry per occupied bed | B53: 220000 | C53: ₦/month
A54: Power and diesel | B54: 2800000 | C54: ₦/month
A55: Insurance, maintenance, licences | B55: 2000000 | C55: ₦/month
A56: Building lease | B56: 100000000 | C56: ₦/year | H56: Unconverted building in Lekki; paid a year ahead from signing; estimate
A57: Lease signed before opening | B57: 6 | C57: months | H57: Building works run in these months
A58: Building works | B58: 200000000 | C58: ₦ | H58: Conversion to a licensable care home; spread over the lease lead
A59: Equipment, furnishing, nurse call, power, pre-opening | B59: 130000000 | C59: ₦
A60: Equipment spend spread over | B60: 5 | C60: months before opening
A61: Deposit per reserved place | B61: 1600000 | C61: ₦ | H61: One month's fee, held not earned
A62: Places reserved by deposit at opening | B62: 7 | C62: places
A64: 3. Mortuary and pathology
A65: Mortuary opens | B65: 10 | C65: month | H65: Month 10 = August 2027; Lekki corridor
A66: Places at opening | B66: 40 | C66: places
A67: Expansion month | B67: 34 | C67: month | H67: Month 34 = August 2029
A68: Places after expansion | B68: 80 | C68: places
A69: Occupancy ceiling | B69: 0.8 | C69: of places
A70: Bodies held at opening | B70: 8 | C70: bodies
A71: Bodies held added a month | B71: 1.6 | C71: bodies
A72: Average stay | B72: 35 | C72: days | H72: Lagos families hold four to eight weeks
A73: Preservation day rate | B73: 18000 | C73: ₦/day | H73: Private homes charge ₦15,000 to ₦50,000 a day
A74: Preparation fee per family | B74: 280000 | C74: ₦ | H74: Embalming, dressing, documentation, local transport
A75: Consumables per family | B75: 45000 | C75: ₦
B76: Month 1 | C76: Value 1 | D76: Month 2 | E76: Value 2 | F76: Month 3 | G76: Value 3
A77: Remains received from abroad a month (ramp) | B77: 16 | C77: 1 | D77: 40 | E77: 4 | F77: 60 | G77: 4
A78: Repatriation fee | B78: 1200000 | C78: ₦
A79: Repatriation direct cost | B79: 0.6 | C79: of revenue
A80: Autopsies a month (ramp) | B80: 10 | C80: 2 | D80: 34 | E80: 8 | F80: 60 | G80: 12
A81: Autopsy fee | B81: 400000 | C81: ₦ | H81: Estimate; no published Lagos price found
A82: Autopsy direct cost | B82: 0.45 | C82: of revenue | H82: Sessional pathologist, histology, toxicology
B83: Month 1 | C83: Value 1 | D83: Month 2 | E83: Value 2 | F83: Month 3 | G83: Value 3
A84: Mortuary staffing (step) | B84: 10 | C84: 7000000 | D84: 34 | E84: 11500000 | H84: ₦/month from each month
A85: Mortuary power (step) | B85: 10 | C85: 3200000 | D85: 34 | E85: 5000000 | H85: ₦/month; cold storage runs 24 hours
A86: Mortuary other running costs | B86: 2000000 | C86: ₦/month
A87: Mortuary site lease | B87: 40000000 | C87: ₦/year | H87: Paid a year ahead; estimate
A88: Lease signed | B88: 7 | C88: month
A89: Build starts | B89: 7 | C89: month
A90: Build: building, cold storage, vehicles | B90: 210000000 | C90: ₦
A91: Build spread over | B91: 3 | C91: months
A92: Expansion build starts | B92: 31 | C92: month
A93: Expansion build | B93: 90000000 | C93: ₦
A94: Expansion spread over | B94: 3 | C94: months
A95: Autopsy suite, month | B95: 9 | C95: month
A96: Autopsy suite | B96: 25000000 | C96: ₦
A98: 4. Software
B99: Month 1 | C99: Value 1 | D99: Month 2 | E99: Value 2 | F99: Month 3 | G99: Value 3
A100: Organisations licensing the platform (ramp) | B100: 13 | C100: 2 | D100: 36 | E100: 15 | F100: 60 | G100: 40 | H100: Agencies, care homes and hospices
A101: Licence fee | B101: 250000 | C101: ₦/month per organisation
A102: Hosting, onboarding and support | B102: 0.3 | C102: of revenue
A104: 5. Central overhead
B105: Month 1 | C105: Value 1 | D105: Month 2 | E105: Value 2 | F105: Month 3 | G105: Value 3
A106: Central team (step) | B106: 1 | C106: 5000000 | D106: 15 | E106: 9000000 | F106: 40 | G106: 12000000 | H106: ₦/month from each month
...

Sheet Volumes
A1: Ilé: volumes
A2: Every count that drives revenue and cost. Linear ramps between the points on Assumptions.
A4: Month | D4: 1 | E4: 2 | F4: 3 | G4: 4 | H4: 5 | I4: 6 | J4: 7 | K4: 8 | L4: 9 | M4: 10 | N4: 11 | O4: 12 | P4: 13 | Q4: 14 | R4: 15 | S4: 16 | T4: 17 | U4: 18 | V4: 19 | W4: 20 | X4: 21 | Y4: 22 | Z4: 23 | AA4: 24 | AB4: 25 | AC4: 26 | AD4: 27 | AE4: 28 | AF4: 29 | AG4: 30 | AH4: 31 | AI4: 32 | AJ4: 33 | AK4: 34 | AL4: 35 | AM4: 36 | AN4: 37 | AO4: 38 | AP4: 39 | AQ4: 40 | AR4: 41 | AS4: 42 | AT4: 43 | AU4: 44 | AV4: 45 | AW4: 46 | AX4: 47 | AY4: 48 | AZ4: 49 | BA4: 50 | BB4: 51 | BC4: 52 | BD4: 53 | BE4: 54 | BF4: 55 | BG4: 56 | BH4: 57 | BI4: 58 | BJ4: 59 | BK4: 60
A5: Period | D5: Nov 2026 | E5: Dec 2026 | F5: Jan 2027 | G5: Feb 2027 | H5: Mar 2027 | I5: Apr 2027 | J5: May 2027 | K5: Jun 2027 | L5: Jul 2027 | M5: Aug 2027 | N5: Sep 2027 | O5: Oct 2027 | P5: Nov 2027 | Q5: Dec 2027 | R5: Jan 2028 | S5: Feb 2028 | T5: Mar 2028 | U5: Apr 2028 | V5: May 2028 | W5: Jun 2028 | X5: Jul 2028 | Y5: Aug 2028 | Z5: Sep 2028 | AA5: Oct 2028 | AB5: Nov 2028 | AC5: Dec 2028 | AD5: Jan 2029 | AE5: Feb 2029 | AF5: Mar 2029 | AG5: Apr 2029 | AH5: May 2029 | AI5: Jun 2029 | AJ5: Jul 2029 | AK5: Aug 2029 | AL5: Sep 2029 | AM5: Oct 2029 | AN5: Nov 2029 | AO5: Dec 2029 | AP5: Jan 2030 | AQ5: Feb 2030 | AR5: Mar 2030 | AS5: Apr 2030 | AT5: May 2030 | AU5: Jun 2030 | AV5: Jul 2030 | AW5: Aug 2030 | AX5: Sep 2030 | AY5: Oct 2030 | AZ5: Nov 2030 | BA5: Dec 2030 | BB5: Jan 2031 | BC5: Feb 2031 | BD5: Mar 2031 | BE5: Apr 2031 | BF5: May 2031 | BG5: Jun 2031 | BH5: Jul 2031 | BI5: Aug 2031 | BJ5: Sep 2031 | BK5: Oct 2031
A6: Model year | D6: =INT((D$4-1)/12)+1 | E6: =INT((E$4-1)/12)+1 | F6: =INT((F$4-1)/12)+1 | G6: =INT((G$4-1)/12)+1 | H6: =INT((H$4-1)/12)+1 | I6: =INT((I$4-1)/12)+1 | J6: =INT((J$4-1)/12)+1 | K6: =INT((K$4-1)/12)+1 | ... BK6: =INT((BK$4-1)/12)+1
A8: 1. Care in the home
A9: Care at home clients | B9: clients | D9: =IF(D$4<HOME_M1,0,IF(D$4<=HOME_M2,HOME_V1+(HOME_V2-HOME_V1)*(D$4-HOME_M1)/(HOME_M2-HOME_M1),IF(D$4<=HOME_M3,HOME_V2+(HOME_V3-HOME_V2)*(D$4-HOME_M2)/(HOME_M3-HOME_M2),HOME_V3))) | E9: =IF(E$4<HOME_M1,0,IF(E$4<=HOME_M2,HOME_V1+(HOME_V2-HOME_V1)*(E$4-HOME_M1)/(HOME_M2-HOME_M1),IF(E$4<=HOME_M3,HOME_V2+(HOME_V3-HOME_V2)*(E$4-HOME_M2)/(HOME_M3-HOME_M2),HOME_V3))) | F9: =IF(F$4<HOME_M1,0,IF(F$4<=HOME_M2,HOME_V1+(HOME_V2-HOME_V1)*(F$4-HOME_M1)/(HOME_M2-HOME_M1),IF(F$4<=HOME_M3,HOME_V2+(HOME_V3-HOME_V2)*(F$4-HOME_M2)/(HOME_M3-HOME_M2),HOME_V3))) | G9: =IF(G$4<HOME_M1,0,IF(G$4<=HOME_M2,HOME_V1+(HOME_V2-HOME_V1)*(G$4-HOME_M1)/(HOME_M2-HOME_M1),IF(G$4<=HOME_M3,HOME_V2+(HOME_V3-HOME_V2)*(G$4-HOME_M2)/(HOME_M3-HOME_M2),HOME_V3))) | H9: =IF(H$4<HOME_M1,0,IF(H$4<=HOME_M2,HOME_V1+(HOME_V2-HOME_V1)*(H$4-HOME_M1)/(HOME_M2-HOME_M1),IF(H$4<=HOME_M3,HOME_V2+(HOME_V3-HOME_V2)*(H$4-HOME_M2)/(HOME_M3-HOME_M2),HOME_V3))) | I9: =IF(I$4<HOME_M1,0,IF(I$4<=HOME_M2,HOME_V1+(HOME_V2-HOME_V1)*(I$4-HOME_M1)/(HOME_M2-HOME_M1),IF(I$4<=HOME_M3,HOME_V2+(HOME_V3-HOME_V2)*(I$4-HOME_M2)/(HOME_M3-HOME_M2),HOME_V3))) | J9: =IF(J$4<HOME_M1,0,IF(J$4<=HOME_M2,HOME_V1+(HOME_V2-HOME_V1)*(J$4-HOME_M1)/(HOME_M2-HOME_M1),IF(J$4<=HOME_M3,HOME_V2+(HOME_V3-HOME_V2)*(J$4-HOME_M2)/(HOME_M3-HOME_M2),HOME_V3))) | K9: =IF(K$4<HOME_M1,0,IF(K$4<=HOME_M2,HOME_V1+(HOME_V2-HOME_V1)*(K$4-HOME_M1)/(HOME_M2-HOME_M1),IF(K$4<=HOME_M3,HOME_V2+(HOME_V3-HOME_V2)*(K$4-HOME_M2)/(HOME_M3-HOME_M2),HOME_V3))) | ... BK9: =IF(BK$4<HOME_M1,0,IF(BK$4<=HOME_M2,HOME_V1+(HOME_V2-HOME_V1)*(BK$4-HOME_M1)/(HOME_M2-HOME_M1),IF(BK$4<=HOME_M3,HOME_V2+(HOME_V3-HOME_V2)*(BK$4-HOME_M2)/(HOME_M3-HOME_M2),HOME_V3)))
A10: Concierge members | B10: members | D10: =IF(D$4<CONC_M1,0,IF(D$4<=CONC_M2,CONC_V1+(CONC_V2-CONC_V1)*(D$4-CONC_M1)/(CONC_M2-CONC_M1),IF(D$4<=CONC_M3,CONC_V2+(CONC_V3-CONC_V2)*(D$4-CONC_M2)/(CONC_M3-CONC_M2),CONC_V3))) | E10: =IF(E$4<CONC_M1,0,IF(E$4<=CONC_M2,CONC_V1+(CONC_V2-CONC_V1)*(E$4-CONC_M1)/(CONC_M2-CONC_M1),IF(E$4<=CONC_M3,CONC_V2+(CONC_V3-CONC_V2)*(E$4-CONC_M2)/(CONC_M3-CONC_M2),CONC_V3))) | F10: =IF(F$4<CONC_M1,0,IF(F$4<=CONC_M2,CONC_V1+(CONC_V2-CONC_V1)*(F$4-CONC_M1)/(CONC_M2-CONC_M1),IF(F$4<=CONC_M3,CONC_V2+(CONC_V3-CONC_V2)*(F$4-CONC_M2)/(CONC_M3-CONC_M2),CONC_V3))) | G10: =IF(G$4<CONC_M1,0,IF(G$4<=CONC_M2,CONC_V1+(CONC_V2-CONC_V1)*(G$4-CONC_M1)/(CONC_M2-CONC_M1),IF(G$4<=CONC_M3,CONC_V2+(CONC_V3-CONC_V2)*(G$4-CONC_M2)/(CONC_M3-CONC_M2),CONC_V3))) | H10: =IF(H$4<CONC_M1,0,IF(H$4<=CONC_M2,CONC_V1+(CONC_V2-CONC_V1)*(H$4-CONC_M1)/(CONC_M2-CONC_M1),IF(H$4<=CONC_M3,CONC_V2+(CONC_V3-CONC_V2)*(H$4-CONC_M2)/(CONC_M3-CONC_M2),CONC_V3))) | I10: =IF(I$4<CONC_M1,0,IF(I$4<=CONC_M2,CONC_V1+(CONC_V2-CONC_V1)*(I$4-CONC_M1)/(CONC_M2-CONC_M1),IF(I$4<=CONC_M3,CONC_V2+(CONC_V3-CONC_V2)*(I$4-CONC_M2)/(CONC_M3-CONC_M2),CONC_V3))) | J10: =IF(J$4<CONC_M1,0,IF(J$4<=CONC_M2,CONC_V1+(CONC_V2-CONC_V1)*(J$4-CONC_M1)/(CONC_M2-CONC_M1),IF(J$4<=CONC_M3,CONC_V2+(CONC_V3-CONC_V2)*(J$4-CONC_M2)/(CONC_M3-CONC_M2),CONC_V3))) | K10: =IF(K$4<CONC_M1,0,IF(K$4<=CONC_M2,CONC_V1+(CONC_V2-CONC_V1)*(K$4-CONC_M1)/(CONC_M2-CONC_M1),IF(K$4<=CONC_M3,CONC_V2+(CONC_V3-CONC_V2)*(K$4-CONC_M2)/(CONC_M3-CONC_M2),CONC_V3))) | ... BK10: =IF(BK$4<CONC_M1,0,IF(BK$4<=CONC_M2,CONC_V1+(CONC_V2-CONC_V1)*(BK$4-CONC_M1)/(CONC_M2-CONC_M1),IF(BK$4<=CONC_M3,CONC_V2+(CONC_V3-CONC_V2)*(BK$4-CONC_M2)/(CONC_M3-CONC_M2),CONC_V3)))
A11: Virtual consultations | B11: a month | D11: =IF(D$4<CONS_M1,0,IF(D$4<=CONS_M2,CONS_V1+(CONS_V2-CONS_V1)*(D$4-CONS_M1)/(CONS_M2-CONS_M1),IF(D$4<=CONS_M3,CONS_V2+(CONS_V3-CONS_V2)*(D$4-CONS_M2)/(CONS_M3-CONS_M2),CONS_V3))) | E11: =IF(E$4<CONS_M1,0,IF(E$4<=CONS_M2,CONS_V1+(CONS_V2-CONS_V1)*(E$4-CONS_M1)/(CONS_M2-CONS_M1),IF(E$4<=CONS_M3,CONS_V2+(CONS_V3-CONS_V2)*(E$4-CONS_M2)/(CONS_M3-CONS_M2),CONS_V3))) | F11: =IF(F$4<CONS_M1,0,IF(F$4<=CONS_M2,CONS_V1+(CONS_V2-CONS_V1)*(F$4-CONS_M1)/(CONS_M2-CONS_M1),IF(F$4<=CONS_M3,CONS_V2+(CONS_V3-CONS_V2)*(F$4-CONS_M2)/(CONS_M3-CONS_M2),CONS_V3))) | G11: =IF(G$4<CONS_M1,0,IF(G$4<=CONS_M2,CONS_V1+(CONS_V2-CONS_V1)*(G$4-CONS_M1)/(CONS_M2-CONS_M1),IF(G$4<=CONS_M3,CONS_V2+(CONS_V3-CONS_V2)*(G$4-CONS_M2)/(CONS_M3-CONS_M2),CONS_V3))) | H11: =IF(H$4<CONS_M1,0,IF(H$4<=CONS_M2,CONS_V1+(CONS_V2-CONS_V1)*(H$4-CONS_M1)/(CONS_M2-CONS_M1),IF(H$4<=CONS_M3,CONS_V2+(CONS_V3-CONS_V2)*(H$4-CONS_M2)/(CONS_M3-CONS_M2),CONS_V3))) | I11: =IF(I$4<CONS_M1,0,IF(I$4<=CONS_M2,CONS_V1+(CONS_V2-CONS_V1)*(I$4-CONS_M1)/(CONS_M2-CONS_M1),IF(I$4<=CONS_M3,CONS_V2+(CONS_V3-CONS_V2)*(I$4-CONS_M2)/(CONS_M3-CONS_M2),CONS_V3))) | J11: =IF(J$4<CONS_M1,0,IF(J$4<=CONS_M2,CONS_V1+(CONS_V2-CONS_V1)*(J$4-CONS_M1)/(CONS_M2-CONS_M1),IF(J$4<=CONS_M3,CONS_V2+(CONS_V3-CONS_V2)*(J$4-CONS_M2)/(CONS_M3-CONS_M2),CONS_V3))) | K11: =IF(K$4<CONS_M1,0,IF(K$4<=CONS_M2,CONS_V1+(CONS_V2-CONS_V1)*(K$4-CONS_M1)/(CONS_M2-CONS_M1),IF(K$4<=CONS_M3,CONS_V2+(CONS_V3-CONS_V2)*(K$4-CONS_M2)/(CONS_M3-CONS_M2),CONS_V3))) | ... BK11: =IF(BK$4<CONS_M1,0,IF(BK$4<=CONS_M2,CONS_V1+(CONS_V2-CONS_V1)*(BK$4-CONS_M1)/(CONS_M2-CONS_M1),IF(BK$4<=CONS_M3,CONS_V2+(CONS_V3-CONS_V2)*(BK$4-CONS_M2)/(CONS_M3-CONS_M2),CONS_V3)))
A12: Post-operative rehab packages begun | B12: a month | D12: =IF(D$4<REHAB_M1,0,IF(D$4<=REHAB_M2,REHAB_V1+(REHAB_V2-REHAB_V1)*(D$4-REHAB_M1)/(REHAB_M2-REHAB_M1),IF(D$4<=REHAB_M3,REHAB_V2+(REHAB_V3-REHAB_V2)*(D$4-REHAB_M2)/(REHAB_M3-REHAB_M2),REHAB_V3))) | E12: =IF(E$4<REHAB_M1,0,IF(E$4<=REHAB_M2,REHAB_V1+(REHAB_V2-REHAB_V1)*(E$4-REHAB_M1)/(REHAB_M2-REHAB_M1),IF(E$4<=REHAB_M3,REHAB_V2+(REHAB_V3-REHAB_V2)*(E$4-REHAB_M2)/(REHAB_M3-REHAB_M2),REHAB_V3))) | F12: =IF(F$4<REHAB_M1,0,IF(F$4<=REHAB_M2,REHAB_V1+(REHAB_V2-REHAB_V1)*(F$4-REHAB_M1)/(REHAB_M2-REHAB_M1),IF(F$4<=REHAB_M3,REHAB_V2+(REHAB_V3-REHAB_V2)*(F$4-REHAB_M2)/(REHAB_M3-REHAB_M2),REHAB_V3))) | G12: =IF(G$4<REHAB_M1,0,IF(G$4<=REHAB_M2,REHAB_V1+(REHAB_V2-REHAB_V1)*(G$4-REHAB_M1)/(REHAB_M2-REHAB_M1),IF(G$4<=REHAB_M3,REHAB_V2+(REHAB_V3-REHAB_V2)*(G$4-REHAB_M2)/(REHAB_M3-REHAB_M2),REHAB_V3))) | H12: =IF(H$4<REHAB_M1,0,IF(H$4<=REHAB_M2,REHAB_V1+(REHAB_V2-REHAB_V1)*(H$4-REHAB_M1)/(REHAB_M2-REHAB_M1),IF(H$4<=REHAB_M3,REHAB_V2+(REHAB_V3-REHAB_V2)*(H$4-REHAB_M2)/(REHAB_M3-REHAB_M2),REHAB_V3))) | I12: =IF(I$4<REHAB_M1,0,IF(I$4<=REHAB_M2,REHAB_V1+(REHAB_V2-REHAB_V1)*(I$4-REHAB_M1)/(REHAB_M2-REHAB_M1),IF(I$4<=REHAB_M3,REHAB_V2+(REHAB_V3-REHAB_V2)*(I$4-REHAB_M2)/(REHAB_M3-REHAB_M2),REHAB_V3))) | J12: =IF(J$4<REHAB_M1,0,IF(J$4<=REHAB_M2,REHAB_V1+(REHAB_V2-REHAB_V1)*(J$4-REHAB_M1)/(REHAB_M2-REHAB_M1),IF(J$4<=REHAB_M3,REHAB_V2+(REHAB_V3-REHAB_V2)*(J$4-REHAB_M2)/(REHAB_M3-REHAB_M2),REHAB_V3))) | K12: =IF(K$4<REHAB_M1,0,IF(K$4<=REHAB_M2,REHAB_V1+(REHAB_V2-REHAB_V1)*(K$4-REHAB_M1)/(REHAB_M2-REHAB_M1),IF(K$4<=REHAB_M3,REHAB_V2+(REHAB_V3-REHAB_V2)*(K$4-REHAB_M2)/(REHAB_M3-REHAB_M2),REHAB_V3))) | ... BK12: =IF(BK$4<REHAB_M1,0,IF(BK$4<=REHAB_M2,REHAB_V1+(REHAB_V2-REHAB_V1)*(BK$4-REHAB_M1)/(REHAB_M2-REHAB_M1),IF(BK$4<=REHAB_M3,REHAB_V2+(REHAB_V3-REHAB_V2)*(BK$4-REHAB_M2)/(REHAB_M3-REHAB_M2),REHAB_V3)))
A13: Palliative patients at home | B13: patients | D13: =IF(D$4<PALLH_M1,0,IF(D$4<=PALLH_M2,PALLH_V1+(PALLH_V2-PALLH_V1)*(D$4-PALLH_M1)/(PALLH_M2-PALLH_M1),IF(D$4<=PALLH_M3,PALLH_V2+(PALLH_V3-PALLH_V2)*(D$4-PALLH_M2)/(PALLH_M3-PALLH_M2),PALLH_V3))) | E13: =IF(E$4<PALLH_M1,0,IF(E$4<=PALLH_M2,PALLH_V1+(PALLH_V2-PALLH_V1)*(E$4-PALLH_M1)/(PALLH_M2-PALLH_M1),IF(E$4<=PALLH_M3,PALLH_V2+(PALLH_V3-PALLH_V2)*(E$4-PALLH_M2)/(PALLH_M3-PALLH_M2),PALLH_V3))) | F13: =IF(F$4<PALLH_M1,0,IF(F$4<=PALLH_M2,PALLH_V1+(PALLH_V2-PALLH_V1)*(F$4-PALLH_M1)/(PALLH_M2-PALLH_M1),IF(F$4<=PALLH_M3,PALLH_V2+(PALLH_V3-PALLH_V2)*(F$4-PALLH_M2)/(PALLH_M3-PALLH_M2),PALLH_V3))) | G13: =IF(G$4<PALLH_M1,0,IF(G$4<=PALLH_M2,PALLH_V1+(PALLH_V2-PALLH_V1)*(G$4-PALLH_M1)/(PALLH_M2-PALLH_M1),IF(G$4<=PALLH_M3,PALLH_V2+(PALLH_V3-PALLH_V2)*(G$4-PALLH_M2)/(PALLH_M3-PALLH_M2),PALLH_V3))) | H13: =IF(H$4<PALLH_M1,0,IF(H$4<=PALLH_M2,PALLH_V1+(PALLH_V2-PALLH_V1)*(H$4-PALLH_M1)/(PALLH_M2-PALLH_M1),IF(H$4<=PALLH_M3,PALLH_V2+(PALLH_V3-PALLH_V2)*(H$4-PALLH_M2)/(PALLH_M3-PALLH_M2),PALLH_V3))) | I13: =IF(I$4<PALLH_M1,0,IF(I$4<=PALLH_M2,PALLH_V1+(PALLH_V2-PALLH_V1)*(I$4-PALLH_M1)/(PALLH_M2-PALLH_M1),IF(I$4<=PALLH_M3,PALLH_V2+(PALLH_V3-PALLH_V2)*(I$4-PALLH_M2)/(PALLH_M3-PALLH_M2),PALLH_V3))) | J13: =IF(J$4<PALLH_M1,0,IF(J$4<=PALLH_M2,PALLH_V1+(PALLH_V2-PALLH_V1)*(J$4-PALLH_M1)/(PALLH_M2-PALLH_M1),IF(J$4<=PALLH_M3,PALLH_V2+(PALLH_V3-PALLH_V2)*(J$4-PALLH_M2)/(PALLH_M3-PALLH_M2),PALLH_V3))) | K13: =IF(K$4<PALLH_M1,0,IF(K$4<=PALLH_M2,PALLH_V1+(PALLH_V2-PALLH_V1)*(K$4-PALLH_M1)/(PALLH_M2-PALLH_M1),IF(K$4<=PALLH_M3,PALLH_V2+(PALLH_V3-PALLH_V2)*(K$4-PALLH_M2)/(PALLH_M3-PALLH_M2),PALLH_V3))) | ... BK13: =IF(BK$4<PALLH_M1,0,IF(BK$4<=PALLH_M2,PALLH_V1+(PALLH_V2-PALLH_V1)*(BK$4-PALLH_M1)/(PALLH_M2-PALLH_M1),IF(BK$4<=PALLH_M3,PALLH_V2+(PALLH_V3-PALLH_V2)*(BK$4-PALLH_M2)/(PALLH_M3-PALLH_M2),PALLH_V3)))
A15: 2. Residential care, occupied beds
A16: Residence one, long-stay | B16: beds | D16: =IF(D$4>=RES1_EFF,MIN(RES_CAP,RES_OPEN_OCC+RES_STEP*RES_SPEED*(D$4-RES1_EFF)),0) | E16: =IF(E$4>=RES1_EFF,MIN(RES_CAP,RES_OPEN_OCC+RES_STEP*RES_SPEED*(E$4-RES1_EFF)),0) | F16: =IF(F$4>=RES1_EFF,MIN(RES_CAP,RES_OPEN_OCC+RES_STEP*RES_SPEED*(F$4-RES1_EFF)),0) | G16: =IF(G$4>=RES1_EFF,MIN(RES_CAP,RES_OPEN_OCC+RES_STEP*RES_SPEED*(G$4-RES1_EFF)),0) | H16: =IF(H$4>=RES1_EFF,MIN(RES_CAP,RES_OPEN_OCC+RES_STEP*RES_SPEED*(H$4-RES1_EFF)),0) | I16: =IF(I$4>=RES1_EFF,MIN(RES_CAP,RES_OPEN_OCC+RES_STEP*RES_SPEED*(I$4-RES1_EFF)),0) | J16: =IF(J$4>=RES1_EFF,MIN(RES_CAP,RES_OPEN_OCC+RES_STEP*RES_SPEED*(J$4-RES1_EFF)),0) | K16: =IF(K$4>=RES1_EFF,MIN(RES_CAP,RES_OPEN_OCC+RES_STEP*RES_SPEED*(K$4-RES1_EFF)),0) | ... BK16: =IF(BK$4>=RES1_EFF,MIN(RES_CAP,RES_OPEN_OCC+RES_STEP*RES_SPEED*(BK$4-RES1_EFF)),0)
A17: Residence one, step-down | B17: beds | D17: =IF(D$4>=RES1_EFF,MIN(STEP_CAP,STEP_OPEN_OCC+STEP_STEP*RES_SPEED*(D$4-RES1_EFF)),0) | E17: =IF(E$4>=RES1_EFF,MIN(STEP_CAP,STEP_OPEN_OCC+STEP_STEP*RES_SPEED*(E$4-RES1_EFF)),0) | F17: =IF(F$4>=RES1_EFF,MIN(STEP_CAP,STEP_OPEN_OCC+STEP_STEP*RES_SPEED*(F$4-RES1_EFF)),0) | G17: =IF(G$4>=RES1_EFF,MIN(STEP_CAP,STEP_OPEN_OCC+STEP_STEP*RES_SPEED*(G$4-RES1_EFF)),0) | H17: =IF(H$4>=RES1_EFF,MIN(STEP_CAP,STEP_OPEN_OCC+STEP_STEP*RES_SPEED*(H$4-RES1_EFF)),0) | I17: =IF(I$4>=RES1_EFF,MIN(STEP_CAP,STEP_OPEN_OCC+STEP_STEP*RES_SPEED*(I$4-RES1_EFF)),0) | J17: =IF(J$4>=RES1_EFF,MIN(STEP_CAP,STEP_OPEN_OCC+STEP_STEP*RES_SPEED*(J$4-RES1_EFF)),0) | K17: =IF(K$4>=RES1_EFF,MIN(STEP_CAP,STEP_OPEN_OCC+STEP_STEP*RES_SPEED*(K$4-RES1_EFF)),0) | ... BK17: =IF(BK$4>=RES1_EFF,MIN(STEP_CAP,STEP_OPEN_OCC+STEP_STEP*RES_SPEED*(BK$4-RES1_EFF)),0)
A18: Residence one, palliative | B18: beds | D18: =IF(D$4>=RES1_EFF,MIN(PALL_CAP,PALL_OPEN_OCC+PALL_STEP*RES_SPEED*(D$4-RES1_EFF)),0) | E18: =IF(E$4>=RES1_EFF,MIN(PALL_CAP,PALL_OPEN_OCC+PALL_STEP*RES_SPEED*(E$4-RES1_EFF)),0) | F18: =IF(F$4>=RES1_EFF,MIN(PALL_CAP,PALL_OPEN_OCC+PALL_STEP*RES_SPEED*(F$4-RES1_EFF)),0) | G18: =IF(G$4>=RES1_EFF,MIN(PALL_CAP,PALL_OPEN_OCC+PALL_STEP*RES_SPEED*(G$4-RES1_EFF)),0) | H18: =IF(H$4>=RES1_EFF,MIN(PALL_CAP,PALL_OPEN_OCC+PALL_STEP*RES_SPEED*(H$4-RES1_EFF)),0) | I18: =IF(I$4>=RES1_EFF,MIN(PALL_CAP,PALL_OPEN_OCC+PALL_STEP*RES_SPEED*(I$4-RES1_EFF)),0) | J18: =IF(J$4>=RES1_EFF,MIN(PALL_CAP,PALL_OPEN_OCC+PALL_STEP*RES_SPEED*(J$4-RES1_EFF)),0) | K18: =IF(K$4>=RES1_EFF,MIN(PALL_CAP,PALL_OPEN_OCC+PALL_STEP*RES_SPEED*(K$4-RES1_EFF)),0) | ... BK18: =IF(BK$4>=RES1_EFF,MIN(PALL_CAP,PALL_OPEN_OCC+PALL_STEP*RES_SPEED*(BK$4-RES1_EFF)),0)
A19: Residence two, long-stay | B19: beds | D19: =IF(D$4>=RES2_EFF,MIN(RES_CAP,RES_OPEN_OCC+RES_STEP*RES_SPEED*(D$4-RES2_EFF)),0) | E19: =IF(E$4>=RES2_EFF,MIN(RES_CAP,RES_OPEN_OCC+RES_STEP*RES_SPEED*(E$4-RES2_EFF)),0) | F19: =IF(F$4>=RES2_EFF,MIN(RES_CAP,RES_OPEN_OCC+RES_STEP*RES_SPEED*(F$4-RES2_EFF)),0) | G19: =IF(G$4>=RES2_EFF,MIN(RES_CAP,RES_OPEN_OCC+RES_STEP*RES_SPEED*(G$4-RES2_EFF)),0) | H19: =IF(H$4>=RES2_EFF,MIN(RES_CAP,RES_OPEN_OCC+RES_STEP*RES_SPEED*(H$4-RES2_EFF)),0) | I19: =IF(I$4>=RES2_EFF,MIN(RES_CAP,RES_OPEN_OCC+RES_STEP*RES_SPEED*(I$4-RES2_EFF)),0) | J19: =IF(J$4>=RES2_EFF,MIN(RES_CAP,RES_OPEN_OCC+RES_STEP*RES_SPEED*(J$4-RES2_EFF)),0) | K19: =IF(K$4>=RES2_EFF,MIN(RES_CAP,RES_OPEN_OCC+RES_STEP*RES_SPEED*(K$4-RES2_EFF)),0) | ... BK19: =IF(BK$4>=RES2_EFF,MIN(RES_CAP,RES_OPEN_OCC+RES_STEP*RES_SPEED*(BK$4-RES2_EFF)),0)
A20: Residence two, step-down | B20: beds | D20: =IF(D$4>=RES2_EFF,MIN(STEP_CAP,STEP_OPEN_OCC+STEP_STEP*RES_SPEED*(D$4-RES2_EFF)),0) | E20: =IF(E$4>=RES2_EFF,MIN(STEP_CAP,STEP_OPEN_OCC+STEP_STEP*RES_SPEED*(E$4-RES2_EFF)),0) | F20: =IF(F$4>=RES2_EFF,MIN(STEP_CAP,STEP_OPEN_OCC+STEP_STEP*RES_SPEED*(F$4-RES2_EFF)),0) | G20: =IF(G$4>=RES2_EFF,MIN(STEP_CAP,STEP_OPEN_OCC+STEP_STEP*RES_SPEED*(G$4-RES2_EFF)),0) | H20: =IF(H$4>=RES2_EFF,MIN(STEP_CAP,STEP_OPEN_OCC+STEP_STEP*RES_SPEED*(H$4-RES2_EFF)),0) | I20: =IF(I$4>=RES2_EFF,MIN(STEP_CAP,STEP_OPEN_OCC+STEP_STEP*RES_SPEED*(I$4-RES2_EFF)),0) | J20: =IF(J$4>=RES2_EFF,MIN(STEP_CAP,STEP_OPEN_OCC+STEP_STEP*RES_SPEED*(J$4-RES2_EFF)),0) | K20: =IF(K$4>=RES2_EFF,MIN(STEP_CAP,STEP_OPEN_OCC+STEP_STEP*RES_SPEED*(K$4-RES2_EFF)),0) | ... BK20: =IF(BK$4>=RES2_EFF,MIN(STEP_CAP,STEP_OPEN_OCC+STEP_STEP*RES_SPEED*(BK$4-RES2_EFF)),0)
A21: Residence two, palliative | B21: beds | D21: =IF(D$4>=RES2_EFF,MIN(PALL_CAP,PALL_OPEN_OCC+PALL_STEP*RES_SPEED*(D$4-RES2_EFF)),0) | E21: =IF(E$4>=RES2_EFF,MIN(PALL_CAP,PALL_OPEN_OCC+PALL_STEP*RES_SPEED*(E$4-RES2_EFF)),0) | F21: =IF(F$4>=RES2_EFF,MIN(PALL_CAP,PALL_OPEN_OCC+PALL_STEP*RES_SPEED*(F$4-RES2_EFF)),0) | G21: =IF(G$4>=RES2_EFF,MIN(PALL_CAP,PALL_OPEN_OCC+PALL_STEP*RES_SPEED*(G$4-RES2_EFF)),0) | H21: =IF(H$4>=RES2_EFF,MIN(PALL_CAP,PALL_OPEN_OCC+PALL_STEP*RES_SPEED*(H$4-RES2_EFF)),0) | I21: =IF(I$4>=RES2_EFF,MIN(PALL_CAP,PALL_OPEN_OCC+PALL_STEP*RES_SPEED*(I$4-RES2_EFF)),0) | J21: =IF(J$4>=RES2_EFF,MIN(PALL_CAP,PALL_OPEN_OCC+PALL_STEP*RES_SPEED*(J$4-RES2_EFF)),0) | K21: =IF(K$4>=RES2_EFF,MIN(PALL_CAP,PALL_OPEN_OCC+PALL_STEP*RES_SPEED*(K$4-RES2_EFF)),0) | ... BK21: =IF(BK$4>=RES2_EFF,MIN(PALL_CAP,PALL_OPEN_OCC+PALL_STEP*RES_SPEED*(BK$4-RES2_EFF)),0)
A22: Occupied beds, both residences | B22: beds | D22: =SUM(D16:D21) | E22: =SUM(E16:E21) | F22: =SUM(F16:F21) | G22: =SUM(G16:G21) | H22: =SUM(H16:H21) | I22: =SUM(I16:I21) | J22: =SUM(J16:J21) | K22: =SUM(K16:K21) | ... BK22: =SUM(BK16:BK21)
A24: 3. Mortuary and pathology
A25: Places | B25: places | D25: =IF(D$4>=MORT_EXP_M,MORT_CAP2,IF(D$4>=MORT_OPEN,MORT_CAP1,0)) | E25: =IF(E$4>=MORT_EXP_M,MORT_CAP2,IF(E$4>=MORT_OPEN,MORT_CAP1,0)) | F25: =IF(F$4>=MORT_EXP_M,MORT_CAP2,IF(F$4>=MORT_OPEN,MORT_CAP1,0)) | G25: =IF(G$4>=MORT_EXP_M,MORT_CAP2,IF(G$4>=MORT_OPEN,MORT_CAP1,0)) | H25: =IF(H$4>=MORT_EXP_M,MORT_CAP2,IF(H$4>=MORT_OPEN,MORT_CAP1,0)) | I25: =IF(I$4>=MORT_EXP_M,MORT_CAP2,IF(I$4>=MORT_OPEN,MORT_CAP1,0)) | J25: =IF(J$4>=MORT_EXP_M,MORT_CAP2,IF(J$4>=MORT_OPEN,MORT_CAP1,0)) | K25: =IF(K$4>=MORT_EXP_M,MORT_CAP2,IF(K$4>=MORT_OPEN,MORT_CAP1,0)) | ... BK25: =IF(BK$4>=MORT_EXP_M,MORT_CAP2,IF(BK$4>=MORT_OPEN,MORT_CAP1,0))
A26: Bodies held on an average day | B26: bodies | D26: =IF(D$4>=MORT_OPEN,MIN(D25*MORT_FILL,MORT_HELD_OPEN+MORT_HELD_STEP*MORT_SPEED*(D$4-MORT_OPEN)),0) | E26: =IF(E$4>=MORT_OPEN,MIN(E25*MORT_FILL,MORT_HELD_OPEN+MORT_HELD_STEP*MORT_SPEED*(E$4-MORT_OPEN)),0) | F26: =IF(F$4>=MORT_OPEN,MIN(F25*MORT_FILL,MORT_HELD_OPEN+MORT_HELD_STEP*MORT_SPEED*(F$4-MORT_OPEN)),0) | G26: =IF(G$4>=MORT_OPEN,MIN(G25*MORT_FILL,MORT_HELD_OPEN+MORT_HELD_STEP*MORT_SPEED*(G$4-MORT_OPEN)),0) | H26: =IF(H$4>=MORT_OPEN,MIN(H25*MORT_FILL,MORT_HELD_OPEN+MORT_HELD_STEP*MORT_SPEED*(H$4-MORT_OPEN)),0) | I26: =IF(I$4>=MORT_OPEN,MIN(I25*MORT_FILL,MORT_HELD_OPEN+MORT_HELD_STEP*MORT_SPEED*(I$4-MORT_OPEN)),0) | J26: =IF(J$4>=MORT_OPEN,MIN(J25*MORT_FILL,MORT_HELD_OPEN+MORT_HELD_STEP*MORT_SPEED*(J$4-MORT_OPEN)),0) | K26: =IF(K$4>=MORT_OPEN,MIN(K25*MORT_FILL,MORT_HELD_OPEN+MORT_HELD_STEP*MORT_SPEED*(K$4-MORT_OPEN)),0) | ... BK26: =IF(BK$4>=MORT_OPEN,MIN(BK25*MORT_FILL,MORT_HELD_OPEN+MORT_HELD_STEP*MORT_SPEED*(BK$4-MORT_OPEN)),0)
A27: Families served | B27: a month | D27: =D26*DAYS_PM/MORT_STAY | E27: =E26*DAYS_PM/MORT_STAY | F27: =F26*DAYS_PM/MORT_STAY | G27: =G26*DAYS_PM/MORT_STAY | H27: =H26*DAYS_PM/MORT_STAY | I27: =I26*DAYS_PM/MORT_STAY | J27: =J26*DAYS_PM/MORT_STAY | K27: =K26*DAYS_PM/MORT_STAY | ... BK27: =BK26*DAYS_PM/MORT_STAY
A28: Remains received from abroad | B28: a month | D28: =IF(D$4>=MORT_OPEN,IF(D$4<REPAT_M1,0,IF(D$4<=REPAT_M2,REPAT_V1+(REPAT_V2-REPAT_V1)*(D$4-REPAT_M1)/(REPAT_M2-REPAT_M1),IF(D$4<=REPAT_M3,REPAT_V2+(REPAT_V3-REPAT_V2)*(D$4-REPAT_M2)/(REPAT_M3-REPAT_M2),REPAT_V3))),0) | E28: =IF(E$4>=MORT_OPEN,IF(E$4<REPAT_M1,0,IF(E$4<=REPAT_M2,REPAT_V1+(REPAT_V2-REPAT_V1)*(E$4-REPAT_M1)/(REPAT_M2-REPAT_M1),IF(E$4<=REPAT_M3,REPAT_V2+(REPAT_V3-REPAT_V2)*(E$4-REPAT_M2)/(REPAT_M3-REPAT_M2),REPAT_V3))),0) | F28: =IF(F$4>=MORT_OPEN,IF(F$4<REPAT_M1,0,IF(F$4<=REPAT_M2,REPAT_V1+(REPAT_V2-REPAT_V1)*(F$4-REPAT_M1)/(REPAT_M2-REPAT_M1),IF(F$4<=REPAT_M3,REPAT_V2+(REPAT_V3-REPAT_V2)*(F$4-REPAT_M2)/(REPAT_M3-REPAT_M2),REPAT_V3))),0) | G28: =IF(G$4>=MORT_OPEN,IF(G$4<REPAT_M1,0,IF(G$4<=REPAT_M2,REPAT_V1+(REPAT_V2-REPAT_V1)*(G$4-REPAT_M1)/(REPAT_M2-REPAT_M1),IF(G$4<=REPAT_M3,REPAT_V2+(REPAT_V3-REPAT_V2)*(G$4-REPAT_M2)/(REPAT_M3-REPAT_M2),REPAT_V3))),0) | H28: =IF(H$4>=MORT_OPEN,IF(H$4<REPAT_M1,0,IF(H$4<=REPAT_M2,REPAT_V1+(REPAT_V2-REPAT_V1)*(H$4-REPAT_M1)/(REPAT_M2-REPAT_M1),IF(H$4<=REPAT_M3,REPAT_V2+(REPAT_V3-REPAT_V2)*(H$4-REPAT_M2)/(REPAT_M3-REPAT_M2),REPAT_V3))),0) | I28: =IF(I$4>=MORT_OPEN,IF(I$4<REPAT_M1,0,IF(I$4<=REPAT_M2,REPAT_V1+(REPAT_V2-REPAT_V1)*(I$4-REPAT_M1)/(REPAT_M2-REPAT_M1),IF(I$4<=REPAT_M3,REPAT_V2+(REPAT_V3-REPAT_V2)*(I$4-REPAT_M2)/(REPAT_M3-REPAT_M2),REPAT_V3))),0) | J28: =IF(J$4>=MORT_OPEN,IF(J$4<REPAT_M1,0,IF(J$4<=REPAT_M2,REPAT_V1+(REPAT_V2-REPAT_V1)*(J$4-REPAT_M1)/(REPAT_M2-REPAT_M1),IF(J$4<=REPAT_M3,REPAT_V2+(REPAT_V3-REPAT_V2)*(J$4-REPAT_M2)/(REPAT_M3-REPAT_M2),REPAT_V3))),0) | K28: =IF(K$4>=MORT_OPEN,IF(K$4<REPAT_M1,0,IF(K$4<=REPAT_M2,REPAT_V1+(REPAT_V2-REPAT_V1)*(K$4-REPAT_M1)/(REPAT_M2-REPAT_M1),IF(K$4<=REPAT_M3,REPAT_V2+(REPAT_V3-REPAT_V2)*(K$4-REPAT_M2)/(REPAT_M3-REPAT_M2),REPAT_V3))),0) | ... BK28: =IF(BK$4>=MORT_OPEN,IF(BK$4<REPAT_M1,0,IF(BK$4<=REPAT_M2,REPAT_V1+(REPAT_V2-REPAT_V1)*(BK$4-REPAT_M1)/(REPAT_M2-REPAT_M1),IF(BK$4<=REPAT_M3,REPAT_V2+(REPAT_V3-REPAT_V2)*(BK$4-REPAT_M2)/(REPAT_M3-REPAT_M2),REPAT_V3))),0)
A29: Autopsies | B29: a month | D29: =IF(D$4>=MORT_OPEN,IF(D$4<AUT_M1,0,IF(D$4<=AUT_M2,AUT_V1+(AUT_V2-AUT_V1)*(D$4-AUT_M1)/(AUT_M2-AUT_M1),IF(D$4<=AUT_M3,AUT_V2+(AUT_V3-AUT_V2)*(D$4-AUT_M2)/(AUT_M3-AUT_M2),AUT_V3))),0) | E29: =IF(E$4>=MORT_OPEN,IF(E$4<AUT_M1,0,IF(E$4<=AUT_M2,AUT_V1+(AUT_V2-AUT_V1)*(E$4-AUT_M1)/(AUT_M2-AUT_M1),IF(E$4<=AUT_M3,AUT_V2+(AUT_V3-AUT_V2)*(E$4-AUT_M2)/(AUT_M3-AUT_M2),AUT_V3))),0) | F29: =IF(F$4>=MORT_OPEN,IF(F$4<AUT_M1,0,IF(F$4<=AUT_M2,AUT_V1+(AUT_V2-AUT_V1)*(F$4-AUT_M1)/(AUT_M2-AUT_M1),IF(F$4<=AUT_M3,AUT_V2+(AUT_V3-AUT_V2)*(F$4-AUT_M2)/(AUT_M3-AUT_M2),AUT_V3))),0) | G29: =IF(G$4>=MORT_OPEN,IF(G$4<AUT_M1,0,IF(G$4<=AUT_M2,AUT_V1+(AUT_V2-AUT_V1)*(G$4-AUT_M1)/(AUT_M2-AUT_M1),IF(G$4<=AUT_M3,AUT_V2+(AUT_V3-AUT_V2)*(G$4-AUT_M2)/(AUT_M3-AUT_M2),AUT_V3))),0) | H29: =IF(H$4>=MORT_OPEN,IF(H$4<AUT_M1,0,IF(H$4<=AUT_M2,AUT_V1+(AUT_V2-AUT_V1)*(H$4-AUT_M1)/(AUT_M2-AUT_M1),IF(H$4<=AUT_M3,AUT_V2+(AUT_V3-AUT_V2)*(H$4-AUT_M2)/(AUT_M3-AUT_M2),AUT_V3))),0) | I29: =IF(I$4>=MORT_OPEN,IF(I$4<AUT_M1,0,IF(I$4<=AUT_M2,AUT_V1+(AUT_V2-AUT_V1)*(I$4-AUT_M1)/(AUT_M2-AUT_M1),IF(I$4<=AUT_M3,AUT_V2+(AUT_V3-AUT_V2)*(I$4-AUT_M2)/(AUT_M3-AUT_M2),AUT_V3))),0) | J29: =IF(J$4>=MORT_OPEN,IF(J$4<AUT_M1,0,IF(J$4<=AUT_M2,AUT_V1+(AUT_V2-AUT_V1)*(J$4-AUT_M1)/(AUT_M2-AUT_M1),IF(J$4<=AUT_M3,AUT_V2+(AUT_V3-AUT_V2)*(J$4-AUT_M2)/(AUT_M3-AUT_M2),AUT_V3))),0) | K29: =IF(K$4>=MORT_OPEN,IF(K$4<AUT_M1,0,IF(K$4<=AUT_M2,AUT_V1+(AUT_V2-AUT_V1)*(K$4-AUT_M1)/(AUT_M2-AUT_M1),IF(K$4<=AUT_M3,AUT_V2+(AUT_V3-AUT_V2)*(K$4-AUT_M2)/(AUT_M3-AUT_M2),AUT_V3))),0) | ... BK29: =IF(BK$4>=MORT_OPEN,IF(BK$4<AUT_M1,0,IF(BK$4<=AUT_M2,AUT_V1+(AUT_V2-AUT_V1)*(BK$4-AUT_M1)/(AUT_M2-AUT_M1),IF(BK$4<=AUT_M3,AUT_V2+(AUT_V3-AUT_V2)*(BK$4-AUT_M2)/(AUT_M3-AUT_M2),AUT_V3))),0)
A31: 4. Software
A32: Organisations licensing | B32: orgs | D32: =IF(D$4<SAAS_M1,0,IF(D$4<=SAAS_M2,SAAS_V1+(SAAS_V2-SAAS_V1)*(D$4-SAAS_M1)/(SAAS_M2-SAAS_M1),IF(D$4<=SAAS_M3,SAAS_V2+(SAAS_V3-SAAS_V2)*(D$4-SAAS_M2)/(SAAS_M3-SAAS_M2),SAAS_V3)))*SAAS_ON | E32: =IF(E$4<SAAS_M1,0,IF(E$4<=SAAS_M2,SAAS_V1+(SAAS_V2-SAAS_V1)*(E$4-SAAS_M1)/(SAAS_M2-SAAS_M1),IF(E$4<=SAAS_M3,SAAS_V2+(SAAS_V3-SAAS_V2)*(E$4-SAAS_M2)/(SAAS_M3-SAAS_M2),SAAS_V3)))*SAAS_ON | F32: =IF(F$4<SAAS_M1,0,IF(F$4<=SAAS_M2,SAAS_V1+(SAAS_V2-SAAS_V1)*(F$4-SAAS_M1)/(SAAS_M2-SAAS_M1),IF(F$4<=SAAS_M3,SAAS_V2+(SAAS_V3-SAAS_V2)*(F$4-SAAS_M2)/(SAAS_M3-SAAS_M2),SAAS_V3)))*SAAS_ON | G32: =IF(G$4<SAAS_M1,0,IF(G$4<=SAAS_M2,SAAS_V1+(SAAS_V2-SAAS_V1)*(G$4-SAAS_M1)/(SAAS_M2-SAAS_M1),IF(G$4<=SAAS_M3,SAAS_V2+(SAAS_V3-SAAS_V2)*(G$4-SAAS_M2)/(SAAS_M3-SAAS_M2),SAAS_V3)))*SAAS_ON | H32: =IF(H$4<SAAS_M1,0,IF(H$4<=SAAS_M2,SAAS_V1+(SAAS_V2-SAAS_V1)*(H$4-SAAS_M1)/(SAAS_M2-SAAS_M1),IF(H$4<=SAAS_M3,SAAS_V2+(SAAS_V3-SAAS_V2)*(H$4-SAAS_M2)/(SAAS_M3-SAAS_M2),SAAS_V3)))*SAAS_ON | I32: =IF(I$4<SAAS_M1,0,IF(I$4<=SAAS_M2,SAAS_V1+(SAAS_V2-SAAS_V1)*(I$4-SAAS_M1)/(SAAS_M2-SAAS_M1),IF(I$4<=SAAS_M3,SAAS_V2+(SAAS_V3-SAAS_V2)*(I$4-SAAS_M2)/(SAAS_M3-SAAS_M2),SAAS_V3)))*SAAS_ON | J32: =IF(J$4<SAAS_M1,0,IF(J$4<=SAAS_M2,SAAS_V1+(SAAS_V2-SAAS_V1)*(J$4-SAAS_M1)/(SAAS_M2-SAAS_M1),IF(J$4<=SAAS_M3,SAAS_V2+(SAAS_V3-SAAS_V2)*(J$4-SAAS_M2)/(SAAS_M3-SAAS_M2),SAAS_V3)))*SAAS_ON | K32: =IF(K$4<SAAS_M1,0,IF(K$4<=SAAS_M2,SAAS_V1+(SAAS_V2-SAAS_V1)*(K$4-SAAS_M1)/(SAAS_M2-SAAS_M1),IF(K$4<=SAAS_M3,SAAS_V2+(SAAS_V3-SAAS_V2)*(K$4-SAAS_M2)/(SAAS_M3-SAAS_M2),SAAS_V3)))*SAAS_ON | ... BK32: =IF(BK$4<SAAS_M1,0,IF(BK$4<=SAAS_M2,SAAS_V1+(SAAS_V2-SAAS_V1)*(BK$4-SAAS_M1)/(SAAS_M2-SAAS_M1),IF(BK$4<=SAAS_M3,SAAS_V2+(SAAS_V3-SAAS_V2)*(BK$4-SAAS_M2)/(SAAS_M3-SAAS_M2),SAAS_V3)))*SAAS_ON

Sheet Revenue
A1: Ilé: revenue
A2: Twelve streams in four business lines. Naira a month.
A4: Month | D4: 1 | E4: 2 | F4: 3 | G4: 4 | H4: 5 | I4: 6 | J4: 7 | K4: 8 | L4: 9 | M4: 10 | N4: 11 | O4: 12 | P4: 13 | Q4: 14 | R4: 15 | S4: 16 | T4: 17 | U4: 18 | V4: 19 | W4: 20 | X4: 21 | Y4: 22 | Z4: 23 | AA4: 24 | AB4: 25 | AC4: 26 | AD4: 27 | AE4: 28 | AF4: 29 | AG4: 30 | AH4: 31 | AI4: 32 | AJ4: 33 | AK4: 34 | AL4: 35 | AM4: 36 | AN4: 37 | AO4: 38 | AP4: 39 | AQ4: 40 | AR4: 41 | AS4: 42 | AT4: 43 | AU4: 44 | AV4: 45 | AW4: 46 | AX4: 47 | AY4: 48 | AZ4: 49 | BA4: 50 | BB4: 51 | BC4: 52 | BD4: 53 | BE4: 54 | BF4: 55 | BG4: 56 | BH4: 57 | BI4: 58 | BJ4: 59 | BK4: 60
A5: Period | D5: Nov 2026 | E5: Dec 2026 | F5: Jan 2027 | G5: Feb 2027 | H5: Mar 2027 | I5: Apr 2027 | J5: May 2027 | K5: Jun 2027 | L5: Jul 2027 | M5: Aug 2027 | N5: Sep 2027 | O5: Oct 2027 | P5: Nov 2027 | Q5: Dec 2027 | R5: Jan 2028 | S5: Feb 2028 | T5: Mar 2028 | U5: Apr 2028 | V5: May 2028 | W5: Jun 2028 | X5: Jul 2028 | Y5: Aug 2028 | Z5: Sep 2028 | AA5: Oct 2028 | AB5: Nov 2028 | AC5: Dec 2028 | AD5: Jan 2029 | AE5: Feb 2029 | AF5: Mar 2029 | AG5: Apr 2029 | AH5: May 2029 | AI5: Jun 2029 | AJ5: Jul 2029 | AK5: Aug 2029 | AL5: Sep 2029 | AM5: Oct 2029 | AN5: Nov 2029 | AO5: Dec 2029 | AP5: Jan 2030 | AQ5: Feb 2030 | AR5: Mar 2030 | AS5: Apr 2030 | AT5: May 2030 | AU5: Jun 2030 | AV5: Jul 2030 | AW5: Aug 2030 | AX5: Sep 2030 | AY5: Oct 2030 | AZ5: Nov 2030 | BA5: Dec 2030 | BB5: Jan 2031 | BC5: Feb 2031 | BD5: Mar 2031 | BE5: Apr 2031 | BF5: May 2031 | BG5: Jun 2031 | BH5: Jul 2031 | BI5: Aug 2031 | BJ5: Sep 2031 | BK5: Oct 2031
A6: Model year | D6: =INT((D$4-1)/12)+1 | E6: =INT((E$4-1)/12)+1 | F6: =INT((F$4-1)/12)+1 | G6: =INT((G$4-1)/12)+1 | H6: =INT((H$4-1)/12)+1 | I6: =INT((I$4-1)/12)+1 | J6: =INT((J$4-1)/12)+1 | K6: =INT((K$4-1)/12)+1 | ... BK6: =INT((BK$4-1)/12)+1
A8: 1. Care in the home
A9: Concierge geriatric care | D9: ='Volumes'!D10*CONC_FEE | E9: ='Volumes'!E10*CONC_FEE | F9: ='Volumes'!F10*CONC_FEE | G9: ='Volumes'!G10*CONC_FEE | H9: ='Volumes'!H10*CONC_FEE | I9: ='Volumes'!I10*CONC_FEE | J9: ='Volumes'!J10*CONC_FEE | K9: ='Volumes'!K10*CONC_FEE | ... BK9: ='Volumes'!BK10*CONC_FEE
A10: Care at home | D10: ='Volumes'!D9*HOME_ARPU | E10: ='Volumes'!E9*HOME_ARPU | F10: ='Volumes'!F9*HOME_ARPU | G10: ='Volumes'!G9*HOME_ARPU | H10: ='Volumes'!H9*HOME_ARPU | I10: ='Volumes'!I9*HOME_ARPU | J10: ='Volumes'!J9*HOME_ARPU | K10: ='Volumes'!K9*HOME_ARPU | ... BK10: ='Volumes'!BK9*HOME_ARPU
A11: Virtual consultations | D11: ='Volumes'!D11*CONS_FEE | E11: ='Volumes'!E11*CONS_FEE | F11: ='Volumes'!F11*CONS_FEE | G11: ='Volumes'!G11*CONS_FEE | H11: ='Volumes'!H11*CONS_FEE | I11: ='Volumes'!I11*CONS_FEE | J11: ='Volumes'!J11*CONS_FEE | K11: ='Volumes'!K11*CONS_FEE | ... BK11: ='Volumes'!BK11*CONS_FEE
A12: Post-operative rehabilitation | D12: ='Volumes'!D12*REHAB_FEE | E12: ='Volumes'!E12*REHAB_FEE | F12: ='Volumes'!F12*REHAB_FEE | G12: ='Volumes'!G12*REHAB_FEE | H12: ='Volumes'!H12*REHAB_FEE | I12: ='Volumes'!I12*REHAB_FEE | J12: ='Volumes'!J12*REHAB_FEE | K12: ='Volumes'!K12*REHAB_FEE | ... BK12: ='Volumes'!BK12*REHAB_FEE
A13: Palliative care at home | D13: ='Volumes'!D13*PALLH_FEE | E13: ='Volumes'!E13*PALLH_FEE | F13: ='Volumes'!F13*PALLH_FEE | G13: ='Volumes'!G13*PALLH_FEE | H13: ='Volumes'!H13*PALLH_FEE | I13: ='Volumes'!I13*PALLH_FEE | J13: ='Volumes'!J13*PALLH_FEE | K13: ='Volumes'!K13*PALLH_FEE | ... BK13: ='Volumes'!BK13*PALLH_FEE
A14: Care in the home | D14: =SUM(D9:D13) | E14: =SUM(E9:E13) | F14: =SUM(F9:F13) | G14: =SUM(G9:G13) | H14: =SUM(H9:H13) | I14: =SUM(I9:I13) | J14: =SUM(J9:J13) | K14: =SUM(K9:K13) | ... BK14: =SUM(BK9:BK13)
A16: 2. Residential care
A17: Residence, long-stay | D17: =('Volumes'!D16+'Volumes'!D19)*RES_FEE | E17: =('Volumes'!E16+'Volumes'!E19)*RES_FEE | F17: =('Volumes'!F16+'Volumes'!F19)*RES_FEE | G17: =('Volumes'!G16+'Volumes'!G19)*RES_FEE | H17: =('Volumes'!H16+'Volumes'!H19)*RES_FEE | I17: =('Volumes'!I16+'Volumes'!I19)*RES_FEE | J17: =('Volumes'!J16+'Volumes'!J19)*RES_FEE | K17: =('Volumes'!K16+'Volumes'!K19)*RES_FEE | ... BK17: =('Volumes'!BK16+'Volumes'!BK19)*RES_FEE
A18: Step-down beds | D18: =('Volumes'!D17+'Volumes'!D20)*DAYS_PM*STEP_DAY | E18: =('Volumes'!E17+'Volumes'!E20)*DAYS_PM*STEP_DAY | F18: =('Volumes'!F17+'Volumes'!F20)*DAYS_PM*STEP_DAY | G18: =('Volumes'!G17+'Volumes'!G20)*DAYS_PM*STEP_DAY | H18: =('Volumes'!H17+'Volumes'!H20)*DAYS_PM*STEP_DAY | I18: =('Volumes'!I17+'Volumes'!I20)*DAYS_PM*STEP_DAY | J18: =('Volumes'!J17+'Volumes'!J20)*DAYS_PM*STEP_DAY | K18: =('Volumes'!K17+'Volumes'!K20)*DAYS_PM*STEP_DAY | ... BK18: =('Volumes'!BK17+'Volumes'!BK20)*DAYS_PM*STEP_DAY
A19: Palliative wing | D19: =('Volumes'!D18+'Volumes'!D21)*PALL_FEE | E19: =('Volumes'!E18+'Volumes'!E21)*PALL_FEE | F19: =('Volumes'!F18+'Volumes'!F21)*PALL_FEE | G19: =('Volumes'!G18+'Volumes'!G21)*PALL_FEE | H19: =('Volumes'!H18+'Volumes'!H21)*PALL_FEE | I19: =('Volumes'!I18+'Volumes'!I21)*PALL_FEE | J19: =('Volumes'!J18+'Volumes'!J21)*PALL_FEE | K19: =('Volumes'!K18+'Volumes'!K21)*PALL_FEE | ... BK19: =('Volumes'!BK18+'Volumes'!BK21)*PALL_FEE
A20: Residential care | D20: =SUM(D17:D19) | E20: =SUM(E17:E19) | F20: =SUM(F17:F19) | G20: =SUM(G17:G19) | H20: =SUM(H17:H19) | I20: =SUM(I17:I19) | J20: =SUM(J17:J19) | K20: =SUM(K17:K19) | ... BK20: =SUM(BK17:BK19)
A22: 3. Mortuary and pathology
A23: Mortuary preservation | D23: ='Volumes'!D26*DAYS_PM*MORT_DAY | E23: ='Volumes'!E26*DAYS_PM*MORT_DAY | F23: ='Volumes'!F26*DAYS_PM*MORT_DAY | G23: ='Volumes'!G26*DAYS_PM*MORT_DAY | H23: ='Volumes'!H26*DAYS_PM*MORT_DAY | I23: ='Volumes'!I26*DAYS_PM*MORT_DAY | J23: ='Volumes'!J26*DAYS_PM*MORT_DAY | K23: ='Volumes'!K26*DAYS_PM*MORT_DAY | ... BK23: ='Volumes'!BK26*DAYS_PM*MORT_DAY
A24: Preparation and repatriation | D24: ='Volumes'!D27*MORT_CASE+'Volumes'!D28*REPAT_FEE | E24: ='Volumes'!E27*MORT_CASE+'Volumes'!E28*REPAT_FEE | F24: ='Volumes'!F27*MORT_CASE+'Volumes'!F28*REPAT_FEE | G24: ='Volumes'!G27*MORT_CASE+'Volumes'!G28*REPAT_FEE | H24: ='Volumes'!H27*MORT_CASE+'Volumes'!H28*REPAT_FEE | I24: ='Volumes'!I27*MORT_CASE+'Volumes'!I28*REPAT_FEE | J24: ='Volumes'!J27*MORT_CASE+'Volumes'!J28*REPAT_FEE | K24: ='Volumes'!K27*MORT_CASE+'Volumes'!K28*REPAT_FEE | ... BK24: ='Volumes'!BK27*MORT_CASE+'Volumes'!BK28*REPAT_FEE
A25: Autopsy and pathology | D25: ='Volumes'!D29*AUT_FEE | E25: ='Volumes'!E29*AUT_FEE | F25: ='Volumes'!F29*AUT_FEE | G25: ='Volumes'!G29*AUT_FEE | H25: ='Volumes'!H29*AUT_FEE | I25: ='Volumes'!I29*AUT_FEE | J25: ='Volumes'!J29*AUT_FEE | K25: ='Volumes'!K29*AUT_FEE | ... BK25: ='Volumes'!BK29*AUT_FEE
A26: Mortuary and pathology | D26: =SUM(D23:D25) | E26: =SUM(E23:E25) | F26: =SUM(F23:F25) | G26: =SUM(G23:G25) | H26: =SUM(H23:H25) | I26: =SUM(I23:I25) | J26: =SUM(J23:J25) | K26: =SUM(K23:K25) | ... BK26: =SUM(BK23:BK25)
A28: 4. Software
A29: Software licences | D29: ='Volumes'!D32*SAAS_FEE | E29: ='Volumes'!E32*SAAS_FEE | F29: ='Volumes'!F32*SAAS_FEE | G29: ='Volumes'!G32*SAAS_FEE | H29: ='Volumes'!H32*SAAS_FEE | I29: ='Volumes'!I32*SAAS_FEE | J29: ='Volumes'!J32*SAAS_FEE | K29: ='Volumes'!K32*SAAS_FEE | ... BK29: ='Volumes'!BK32*SAAS_FEE
A30: Software | D30: =D29 | E30: =E29 | F30: =F29 | G30: =G29 | H30: =H29 | I30: =I29 | J30: =J29 | K30: =K29 | ... BK30: =BK29
A32: Revenue | D32: =D14+D20+D26+D30 | E32: =E14+E20+E26+E30 | F32: =F14+F20+F26+F30 | G32: =G14+G20+G26+G30 | H32: =H14+H20+H26+H30 | I32: =I14+I20+I26+I30 | J32: =J14+J20+J26+J30 | K32: =K14+K20+K26+K30 | ... BK32: =BK14+BK20+BK26+BK30

Sheet Costs
A1: Ilé: costs
A2: Four buckets: direct, site operating, leases, central. Naira a month.
A4: Month | D4: 1 | E4: 2 | F4: 3 | G4: 4 | H4: 5 | I4: 6 | J4: 7 | K4: 8 | L4: 9 | M4: 10 | N4: 11 | O4: 12 | P4: 13 | Q4: 14 | R4: 15 | S4: 16 | T4: 17 | U4: 18 | V4: 19 | W4: 20 | X4: 21 | Y4: 22 | Z4: 23 | AA4: 24 | AB4: 25 | AC4: 26 | AD4: 27 | AE4: 28 | AF4: 29 | AG4: 30 | AH4: 31 | AI4: 32 | AJ4: 33 | AK4: 34 | AL4: 35 | AM4: 36 | AN4: 37 | AO4: 38 | AP4: 39 | AQ4: 40 | AR4: 41 | AS4: 42 | AT4: 43 | AU4: 44 | AV4: 45 | AW4: 46 | AX4: 47 | AY4: 48 | AZ4: 49 | BA4: 50 | BB4: 51 | BC4: 52 | BD4: 53 | BE4: 54 | BF4: 55 | BG4: 56 | BH4: 57 | BI4: 58 | BJ4: 59 | BK4: 60
A5: Period | D5: Nov 2026 | E5: Dec 2026 | F5: Jan 2027 | G5: Feb 2027 | H5: Mar 2027 | I5: Apr 2027 | J5: May 2027 | K5: Jun 2027 | L5: Jul 2027 | M5: Aug 2027 | N5: Sep 2027 | O5: Oct 2027 | P5: Nov 2027 | Q5: Dec 2027 | R5: Jan 2028 | S5: Feb 2028 | T5: Mar 2028 | U5: Apr 2028 | V5: May 2028 | W5: Jun 2028 | X5: Jul 2028 | Y5: Aug 2028 | Z5: Sep 2028 | AA5: Oct 2028 | AB5: Nov 2028 | AC5: Dec 2028 | AD5: Jan 2029 | AE5: Feb 2029 | AF5: Mar 2029 | AG5: Apr 2029 | AH5: May 2029 | AI5: Jun 2029 | AJ5: Jul 2029 | AK5: Aug 2029 | AL5: Sep 2029 | AM5: Oct 2029 | AN5: Nov 2029 | AO5: Dec 2029 | AP5: Jan 2030 | AQ5: Feb 2030 | AR5: Mar 2030 | AS5: Apr 2030 | AT5: May 2030 | AU5: Jun 2030 | AV5: Jul 2030 | AW5: Aug 2030 | AX5: Sep 2030 | AY5: Oct 2030 | AZ5: Nov 2030 | BA5: Dec 2030 | BB5: Jan 2031 | BC5: Feb 2031 | BD5: Mar 2031 | BE5: Apr 2031 | BF5: May 2031 | BG5: Jun 2031 | BH5: Jul 2031 | BI5: Aug 2031 | BJ5: Sep 2031 | BK5: Oct 2031
A6: Model year | D6: =INT((D$4-1)/12)+1 | E6: =INT((E$4-1)/12)+1 | F6: =INT((F$4-1)/12)+1 | G6: =INT((G$4-1)/12)+1 | H6: =INT((H$4-1)/12)+1 | I6: =INT((I$4-1)/12)+1 | J6: =INT((J$4-1)/12)+1 | K6: =INT((K$4-1)/12)+1 | ... BK6: =INT((BK$4-1)/12)+1
A8: A. Direct costs, by stream
A9: Concierge | D9: ='Revenue'!D9*CONC_DIRECT | E9: ='Revenue'!E9*CONC_DIRECT | F9: ='Revenue'!F9*CONC_DIRECT | G9: ='Revenue'!G9*CONC_DIRECT | H9: ='Revenue'!H9*CONC_DIRECT | I9: ='Revenue'!I9*CONC_DIRECT | J9: ='Revenue'!J9*CONC_DIRECT | K9: ='Revenue'!K9*CONC_DIRECT | ... BK9: ='Revenue'!BK9*CONC_DIRECT
A10: Care at home | D10: ='Revenue'!D10*HOME_DIRECT | E10: ='Revenue'!E10*HOME_DIRECT | F10: ='Revenue'!F10*HOME_DIRECT | G10: ='Revenue'!G10*HOME_DIRECT | H10: ='Revenue'!H10*HOME_DIRECT | I10: ='Revenue'!I10*HOME_DIRECT | J10: ='Revenue'!J10*HOME_DIRECT | K10: ='Revenue'!K10*HOME_DIRECT | ... BK10: ='Revenue'!BK10*HOME_DIRECT
A11: Virtual consultations | D11: ='Revenue'!D11*CONS_DIRECT | E11: ='Revenue'!E11*CONS_DIRECT | F11: ='Revenue'!F11*CONS_DIRECT | G11: ='Revenue'!G11*CONS_DIRECT | H11: ='Revenue'!H11*CONS_DIRECT | I11: ='Revenue'!I11*CONS_DIRECT | J11: ='Revenue'!J11*CONS_DIRECT | K11: ='Revenue'!K11*CONS_DIRECT | ... BK11: ='Revenue'!BK11*CONS_DIRECT
A12: Post-operative rehabilitation | D12: ='Revenue'!D12*REHAB_DIRECT | E12: ='Revenue'!E12*REHAB_DIRECT | F12: ='Revenue'!F12*REHAB_DIRECT | G12: ='Revenue'!G12*REHAB_DIRECT | H12: ='Revenue'!H12*REHAB_DIRECT | I12: ='Revenue'!I12*REHAB_DIRECT | J12: ='Revenue'!J12*REHAB_DIRECT | K12: ='Revenue'!K12*REHAB_DIRECT | ... BK12: ='Revenue'!BK12*REHAB_DIRECT
A13: Palliative care at home | D13: ='Revenue'!D13*PALLH_DIRECT | E13: ='Revenue'!E13*PALLH_DIRECT | F13: ='Revenue'!F13*PALLH_DIRECT | G13: ='Revenue'!G13*PALLH_DIRECT | H13: ='Revenue'!H13*PALLH_DIRECT | I13: ='Revenue'!I13*PALLH_DIRECT | J13: ='Revenue'!J13*PALLH_DIRECT | K13: ='Revenue'!K13*PALLH_DIRECT | ... BK13: ='Revenue'!BK13*PALLH_DIRECT
A14: Mortuary consumables per family | D14: ='Volumes'!D27*MORT_CASE_COST | E14: ='Volumes'!E27*MORT_CASE_COST | F14: ='Volumes'!F27*MORT_CASE_COST | G14: ='Volumes'!G27*MORT_CASE_COST | H14: ='Volumes'!H27*MORT_CASE_COST | I14: ='Volumes'!I27*MORT_CASE_COST | J14: ='Volumes'!J27*MORT_CASE_COST | K14: ='Volumes'!K27*MORT_CASE_COST | ... BK14: ='Volumes'!BK27*MORT_CASE_COST
A15: Repatriation | D15: ='Volumes'!D28*REPAT_FEE*REPAT_DIRECT | E15: ='Volumes'!E28*REPAT_FEE*REPAT_DIRECT | F15: ='Volumes'!F28*REPAT_FEE*REPAT_DIRECT | G15: ='Volumes'!G28*REPAT_FEE*REPAT_DIRECT | H15: ='Volumes'!H28*REPAT_FEE*REPAT_DIRECT | I15: ='Volumes'!I28*REPAT_FEE*REPAT_DIRECT | J15: ='Volumes'!J28*REPAT_FEE*REPAT_DIRECT | K15: ='Volumes'!K28*REPAT_FEE*REPAT_DIRECT | ... BK15: ='Volumes'!BK28*REPAT_FEE*REPAT_DIRECT
A16: Autopsy and pathology | D16: ='Revenue'!D25*AUT_DIRECT | E16: ='Revenue'!E25*AUT_DIRECT | F16: ='Revenue'!F25*AUT_DIRECT | G16: ='Revenue'!G25*AUT_DIRECT | H16: ='Revenue'!H25*AUT_DIRECT | I16: ='Revenue'!I25*AUT_DIRECT | J16: ='Revenue'!J25*AUT_DIRECT | K16: ='Revenue'!K25*AUT_DIRECT | ... BK16: ='Revenue'!BK25*AUT_DIRECT
A17: Software hosting and support | D17: ='Revenue'!D29*SAAS_DIRECT | E17: ='Revenue'!E29*SAAS_DIRECT | F17: ='Revenue'!F29*SAAS_DIRECT | G17: ='Revenue'!G29*SAAS_DIRECT | H17: ='Revenue'!H29*SAAS_DIRECT | I17: ='Revenue'!I29*SAAS_DIRECT | J17: ='Revenue'!J29*SAAS_DIRECT | K17: ='Revenue'!K29*SAAS_DIRECT | ... BK17: ='Revenue'!BK29*SAAS_DIRECT
A18: Direct costs | D18: =SUM(D9:D17) | E18: =SUM(E9:E17) | F18: =SUM(F9:F17) | G18: =SUM(G9:G17) | H18: =SUM(H9:H17) | I18: =SUM(I9:I17) | J18: =SUM(J9:J17) | K18: =SUM(K9:K17) | ... BK18: =SUM(BK9:BK17)
A20: B. Site operating costs
A21: Residence one, staffing | D21: =IF(D$4>=RES1_EFF,RES_STAFF,IF(OR(D$4=RES1_EFF-1,D$4=RES1_EFF-2),RES_STAFF*PREOPEN,0)) | E21: =IF(E$4>=RES1_EFF,RES_STAFF,IF(OR(E$4=RES1_EFF-1,E$4=RES1_EFF-2),RES_STAFF*PREOPEN,0)) | F21: =IF(F$4>=RES1_EFF,RES_STAFF,IF(OR(F$4=RES1_EFF-1,F$4=RES1_EFF-2),RES_STAFF*PREOPEN,0)) | G21: =IF(G$4>=RES1_EFF,RES_STAFF,IF(OR(G$4=RES1_EFF-1,G$4=RES1_EFF-2),RES_STAFF*PREOPEN,0)) | H21: =IF(H$4>=RES1_EFF,RES_STAFF,IF(OR(H$4=RES1_EFF-1,H$4=RES1_EFF-2),RES_STAFF*PREOPEN,0)) | I21: =IF(I$4>=RES1_EFF,RES_STAFF,IF(OR(I$4=RES1_EFF-1,I$4=RES1_EFF-2),RES_STAFF*PREOPEN,0)) | J21: =IF(J$4>=RES1_EFF,RES_STAFF,IF(OR(J$4=RES1_EFF-1,J$4=RES1_EFF-2),RES_STAFF*PREOPEN,0)) | K21: =IF(K$4>=RES1_EFF,RES_STAFF,IF(OR(K$4=RES1_EFF-1,K$4=RES1_EFF-2),RES_STAFF*PREOPEN,0)) | ... BK21: =IF(BK$4>=RES1_EFF,RES_STAFF,IF(OR(BK$4=RES1_EFF-1,BK$4=RES1_EFF-2),RES_STAFF*PREOPEN,0))
A22: Residence one, food and consumables | D22: =('Volumes'!D16+'Volumes'!D17+'Volumes'!D18)*RES_PER_BED | E22: =('Volumes'!E16+'Volumes'!E17+'Volumes'!E18)*RES_PER_BED | F22: =('Volumes'!F16+'Volumes'!F17+'Volumes'!F18)*RES_PER_BED | G22: =('Volumes'!G16+'Volumes'!G17+'Volumes'!G18)*RES_PER_BED | H22: =('Volumes'!H16+'Volumes'!H17+'Volumes'!H18)*RES_PER_BED | I22: =('Volumes'!I16+'Volumes'!I17+'Volumes'!I18)*RES_PER_BED | J22: =('Volumes'!J16+'Volumes'!J17+'Volumes'!J18)*RES_PER_BED | K22: =('Volumes'!K16+'Volumes'!K17+'Volumes'!K18)*RES_PER_BED | ... BK22: =('Volumes'!BK16+'Volumes'!BK17+'Volumes'!BK18)*RES_PER_BED
A23: Residence one, power and diesel | D23: =IF(D$4>=RES1_EFF,RES_UTIL,0) | E23: =IF(E$4>=RES1_EFF,RES_UTIL,0) | F23: =IF(F$4>=RES1_EFF,RES_UTIL,0) | G23: =IF(G$4>=RES1_EFF,RES_UTIL,0) | H23: =IF(H$4>=RES1_EFF,RES_UTIL,0) | I23: =IF(I$4>=RES1_EFF,RES_UTIL,0) | J23: =IF(J$4>=RES1_EFF,RES_UTIL,0) | K23: =IF(K$4>=RES1_EFF,RES_UTIL,0) | ... BK23: =IF(BK$4>=RES1_EFF,RES_UTIL,0)
A24: Residence one, insurance and maintenance | D24: =IF(D$4>=RES1_EFF,RES_OTHER,0) | E24: =IF(E$4>=RES1_EFF,RES_OTHER,0) | F24: =IF(F$4>=RES1_EFF,RES_OTHER,0) | G24: =IF(G$4>=RES1_EFF,RES_OTHER,0) | H24: =IF(H$4>=RES1_EFF,RES_OTHER,0) | I24: =IF(I$4>=RES1_EFF,RES_OTHER,0) | J24: =IF(J$4>=RES1_EFF,RES_OTHER,0) | K24: =IF(K$4>=RES1_EFF,RES_OTHER,0) | ... BK24: =IF(BK$4>=RES1_EFF,RES_OTHER,0)
A25: Residence two, staffing | D25: =IF(D$4>=RES2_EFF,RES_STAFF,IF(OR(D$4=RES2_EFF-1,D$4=RES2_EFF-2),RES_STAFF*PREOPEN,0)) | E25: =IF(E$4>=RES2_EFF,RES_STAFF,IF(OR(E$4=RES2_EFF-1,E$4=RES2_EFF-2),RES_STAFF*PREOPEN,0)) | F25: =IF(F$4>=RES2_EFF,RES_STAFF,IF(OR(F$4=RES2_EFF-1,F$4=RES2_EFF-2),RES_STAFF*PREOPEN,0)) | G25: =IF(G$4>=RES2_EFF,RES_STAFF,IF(OR(G$4=RES2_EFF-1,G$4=RES2_EFF-2),RES_STAFF*PREOPEN,0)) | H25: =IF(H$4>=RES2_EFF,RES_STAFF,IF(OR(H$4=RES2_EFF-1,H$4=RES2_EFF-2),RES_STAFF*PREOPEN,0)) | I25: =IF(I$4>=RES2_EFF,RES_STAFF,IF(OR(I$4=RES2_EFF-1,I$4=RES2_EFF-2),RES_STAFF*PREOPEN,0)) | J25: =IF(J$4>=RES2_EFF,RES_STAFF,IF(OR(J$4=RES2_EFF-1,J$4=RES2_EFF-2),RES_STAFF*PREOPEN,0)) | K25: =IF(K$4>=RES2_EFF,RES_STAFF,IF(OR(K$4=RES2_EFF-1,K$4=RES2_EFF-2),RES_STAFF*PREOPEN,0)) | ... BK25: =IF(BK$4>=RES2_EFF,RES_STAFF,IF(OR(BK$4=RES2_EFF-1,BK$4=RES2_EFF-2),RES_STAFF*PREOPEN,0))
A26: Residence two, food and consumables | D26: =('Volumes'!D19+'Volumes'!D20+'Volumes'!D21)*RES_PER_BED | E26: =('Volumes'!E19+'Volumes'!E20+'Volumes'!E21)*RES_PER_BED | F26: =('Volumes'!F19+'Volumes'!F20+'Volumes'!F21)*RES_PER_BED | G26: =('Volumes'!G19+'Volumes'!G20+'Volumes'!G21)*RES_PER_BED | H26: =('Volumes'!H19+'Volumes'!H20+'Volumes'!H21)*RES_PER_BED | I26: =('Volumes'!I19+'Volumes'!I20+'Volumes'!I21)*RES_PER_BED | J26: =('Volumes'!J19+'Volumes'!J20+'Volumes'!J21)*RES_PER_BED | K26: =('Volumes'!K19+'Volumes'!K20+'Volumes'!K21)*RES_PER_BED | ... BK26: =('Volumes'!BK19+'Volumes'!BK20+'Volumes'!BK21)*RES_PER_BED
A27: Residence two, power and diesel | D27: =IF(D$4>=RES2_EFF,RES_UTIL,0) | E27: =IF(E$4>=RES2_EFF,RES_UTIL,0) | F27: =IF(F$4>=RES2_EFF,RES_UTIL,0) | G27: =IF(G$4>=RES2_EFF,RES_UTIL,0) | H27: =IF(H$4>=RES2_EFF,RES_UTIL,0) | I27: =IF(I$4>=RES2_EFF,RES_UTIL,0) | J27: =IF(J$4>=RES2_EFF,RES_UTIL,0) | K27: =IF(K$4>=RES2_EFF,RES_UTIL,0) | ... BK27: =IF(BK$4>=RES2_EFF,RES_UTIL,0)
A28: Residence two, insurance and maintenance | D28: =IF(D$4>=RES2_EFF,RES_OTHER,0) | E28: =IF(E$4>=RES2_EFF,RES_OTHER,0) | F28: =IF(F$4>=RES2_EFF,RES_OTHER,0) | G28: =IF(G$4>=RES2_EFF,RES_OTHER,0) | H28: =IF(H$4>=RES2_EFF,RES_OTHER,0) | I28: =IF(I$4>=RES2_EFF,RES_OTHER,0) | J28: =IF(J$4>=RES2_EFF,RES_OTHER,0) | K28: =IF(K$4>=RES2_EFF,RES_OTHER,0) | ... BK28: =IF(BK$4>=RES2_EFF,RES_OTHER,0)
A29: Mortuary, staffing | D29: =IF(D$4>=MSTAFF_M2,MSTAFF_V2,IF(D$4>=MSTAFF_M1,MSTAFF_V1,0)) | E29: =IF(E$4>=MSTAFF_M2,MSTAFF_V2,IF(E$4>=MSTAFF_M1,MSTAFF_V1,0)) | F29: =IF(F$4>=MSTAFF_M2,MSTAFF_V2,IF(F$4>=MSTAFF_M1,MSTAFF_V1,0)) | G29: =IF(G$4>=MSTAFF_M2,MSTAFF_V2,IF(G$4>=MSTAFF_M1,MSTAFF_V1,0)) | H29: =IF(H$4>=MSTAFF_M2,MSTAFF_V2,IF(H$4>=MSTAFF_M1,MSTAFF_V1,0)) | I29: =IF(I$4>=MSTAFF_M2,MSTAFF_V2,IF(I$4>=MSTAFF_M1,MSTAFF_V1,0)) | J29: =IF(J$4>=MSTAFF_M2,MSTAFF_V2,IF(J$4>=MSTAFF_M1,MSTAFF_V1,0)) | K29: =IF(K$4>=MSTAFF_M2,MSTAFF_V2,IF(K$4>=MSTAFF_M1,MSTAFF_V1,0)) | ... BK29: =IF(BK$4>=MSTAFF_M2,MSTAFF_V2,IF(BK$4>=MSTAFF_M1,MSTAFF_V1,0))
A30: Mortuary, power | D30: =IF(D$4>=MPOWER_M2,MPOWER_V2,IF(D$4>=MPOWER_M1,MPOWER_V1,0)) | E30: =IF(E$4>=MPOWER_M2,MPOWER_V2,IF(E$4>=MPOWER_M1,MPOWER_V1,0)) | F30: =IF(F$4>=MPOWER_M2,MPOWER_V2,IF(F$4>=MPOWER_M1,MPOWER_V1,0)) | G30: =IF(G$4>=MPOWER_M2,MPOWER_V2,IF(G$4>=MPOWER_M1,MPOWER_V1,0)) | H30: =IF(H$4>=MPOWER_M2,MPOWER_V2,IF(H$4>=MPOWER_M1,MPOWER_V1,0)) | I30: =IF(I$4>=MPOWER_M2,MPOWER_V2,IF(I$4>=MPOWER_M1,MPOWER_V1,0)) | J30: =IF(J$4>=MPOWER_M2,MPOWER_V2,IF(J$4>=MPOWER_M1,MPOWER_V1,0)) | K30: =IF(K$4>=MPOWER_M2,MPOWER_V2,IF(K$4>=MPOWER_M1,MPOWER_V1,0)) | ... BK30: =IF(BK$4>=MPOWER_M2,MPOWER_V2,IF(BK$4>=MPOWER_M1,MPOWER_V1,0))
A31: Mortuary, other running costs | D31: =IF(D$4>=MORT_OPEN,MORT_OTHER,0) | E31: =IF(E$4>=MORT_OPEN,MORT_OTHER,0) | F31: =IF(F$4>=MORT_OPEN,MORT_OTHER,0) | G31: =IF(G$4>=MORT_OPEN,MORT_OTHER,0) | H31: =IF(H$4>=MORT_OPEN,MORT_OTHER,0) | I31: =IF(I$4>=MORT_OPEN,MORT_OTHER,0) | J31: =IF(J$4>=MORT_OPEN,MORT_OTHER,0) | K31: =IF(K$4>=MORT_OPEN,MORT_OTHER,0) | ... BK31: =IF(BK$4>=MORT_OPEN,MORT_OTHER,0)
A32: Site operating costs | D32: =SUM(D21:D31) | E32: =SUM(E21:E31) | F32: =SUM(F21:F31) | G32: =SUM(G21:G31) | H32: =SUM(H21:H31) | I32: =SUM(I21:I31) | J32: =SUM(J21:J31) | K32: =SUM(K21:K31) | ... BK32: =SUM(BK21:BK31)
A34: C. Leases, charged monthly
A35: Residence one building | D35: =IF(D$4>=RES1_EFF-LEASE_LEAD,RES_LEASE_YR/12,0) | E35: =IF(E$4>=RES1_EFF-LEASE_LEAD,RES_LEASE_YR/12,0) | F35: =IF(F$4>=RES1_EFF-LEASE_LEAD,RES_LEASE_YR/12,0) | G35: =IF(G$4>=RES1_EFF-LEASE_LEAD,RES_LEASE_YR/12,0) | H35: =IF(H$4>=RES1_EFF-LEASE_LEAD,RES_LEASE_YR/12,0) | I35: =IF(I$4>=RES1_EFF-LEASE_LEAD,RES_LEASE_YR/12,0) | J35: =IF(J$4>=RES1_EFF-LEASE_LEAD,RES_LEASE_YR/12,0) | K35: =IF(K$4>=RES1_EFF-LEASE_LEAD,RES_LEASE_YR/12,0) | ... BK35: =IF(BK$4>=RES1_EFF-LEASE_LEAD,RES_LEASE_YR/12,0)
A36: Residence two building | D36: =IF(D$4>=RES2_EFF-LEASE_LEAD,RES_LEASE_YR/12,0) | E36: =IF(E$4>=RES2_EFF-LEASE_LEAD,RES_LEASE_YR/12,0) | F36: =IF(F$4>=RES2_EFF-LEASE_LEAD,RES_LEASE_YR/12,0) | G36: =IF(G$4>=RES2_EFF-LEASE_LEAD,RES_LEASE_YR/12,0) | H36: =IF(H$4>=RES2_EFF-LEASE_LEAD,RES_LEASE_YR/12,0) | I36: =IF(I$4>=RES2_EFF-LEASE_LEAD,RES_LEASE_YR/12,0) | J36: =IF(J$4>=RES2_EFF-LEASE_LEAD,RES_LEASE_YR/12,0) | K36: =IF(K$4>=RES2_EFF-LEASE_LEAD,RES_LEASE_YR/12,0) | ... BK36: =IF(BK$4>=RES2_EFF-LEASE_LEAD,RES_LEASE_YR/12,0)
A37: Mortuary site | D37: =IF(D$4>=MORT_LEASE_FROM,MORT_LEASE_YR/12,0) | E37: =IF(E$4>=MORT_LEASE_FROM,MORT_LEASE_YR/12,0) | F37: =IF(F$4>=MORT_LEASE_FROM,MORT_LEASE_YR/12,0) | G37: =IF(G$4>=MORT_LEASE_FROM,MORT_LEASE_YR/12,0) | H37: =IF(H$4>=MORT_LEASE_FROM,MORT_LEASE_YR/12,0) | I37: =IF(I$4>=MORT_LEASE_FROM,MORT_LEASE_YR/12,0) | J37: =IF(J$4>=MORT_LEASE_FROM,MORT_LEASE_YR/12,0) | K37: =IF(K$4>=MORT_LEASE_FROM,MORT_LEASE_YR/12,0) | ... BK37: =IF(BK$4>=MORT_LEASE_FROM,MORT_LEASE_YR/12,0)
A38: Leases | D38: =SUM(D35:D37) | E38: =SUM(E35:E37) | F38: =SUM(F35:F37) | G38: =SUM(G35:G37) | H38: =SUM(H35:H37) | I38: =SUM(I35:I37) | J38: =SUM(J35:J37) | K38: =SUM(K35:K37) | ... BK38: =SUM(BK35:BK37)
A40: D. Central overhead
A41: Central team | D41: =IF(D$4>=CENT_M3,CENT_V3,IF(D$4>=CENT_M2,CENT_V2,IF(D$4>=CENT_M1,CENT_V1,0))) | E41: =IF(E$4>=CENT_M3,CENT_V3,IF(E$4>=CENT_M2,CENT_V2,IF(E$4>=CENT_M1,CENT_V1,0))) | F41: =IF(F$4>=CENT_M3,CENT_V3,IF(F$4>=CENT_M2,CENT_V2,IF(F$4>=CENT_M1,CENT_V1,0))) | G41: =IF(G$4>=CENT_M3,CENT_V3,IF(G$4>=CENT_M2,CENT_V2,IF(G$4>=CENT_M1,CENT_V1,0))) | H41: =IF(H$4>=CENT_M3,CENT_V3,IF(H$4>=CENT_M2,CENT_V2,IF(H$4>=CENT_M1,CENT_V1,0))) | I41: =IF(I$4>=CENT_M3,CENT_V3,IF(I$4>=CENT_M2,CENT_V2,IF(I$4>=CENT_M1,CENT_V1,0))) | J41: =IF(J$4>=CENT_M3,CENT_V3,IF(J$4>=CENT_M2,CENT_V2,IF(J$4>=CENT_M1,CENT_V1,0))) | K41: =IF(K$4>=CENT_M3,CENT_V3,IF(K$4>=CENT_M2,CENT_V2,IF(K$4>=CENT_M1,CENT_V1,0))) | ... BK41: =IF(BK$4>=CENT_M3,CENT_V3,IF(BK$4>=CENT_M2,CENT_V2,IF(BK$4>=CENT_M1,CENT_V1,0)))
A42: Marketing | D42: =IF(D$4>=MKT_M2,MKT_V2,IF(D$4>=MKT_M1,MKT_V1,0)) | E42: =IF(E$4>=MKT_M2,MKT_V2,IF(E$4>=MKT_M1,MKT_V1,0)) | F42: =IF(F$4>=MKT_M2,MKT_V2,IF(F$4>=MKT_M1,MKT_V1,0)) | G42: =IF(G$4>=MKT_M2,MKT_V2,IF(G$4>=MKT_M1,MKT_V1,0)) | H42: =IF(H$4>=MKT_M2,MKT_V2,IF(H$4>=MKT_M1,MKT_V1,0)) | I42: =IF(I$4>=MKT_M2,MKT_V2,IF(I$4>=MKT_M1,MKT_V1,0)) | J42: =IF(J$4>=MKT_M2,MKT_V2,IF(J$4>=MKT_M1,MKT_V1,0)) | K42: =IF(K$4>=MKT_M2,MKT_V2,IF(K$4>=MKT_M1,MKT_V1,0)) | ... BK42: =IF(BK$4>=MKT_M2,MKT_V2,IF(BK$4>=MKT_M1,MKT_V1,0))
A43: Central overhead | D43: =SUM(D41:D42) | E43: =SUM(E41:E42) | F43: =SUM(F41:F42) | G43: =SUM(G41:G42) | H43: =SUM(H41:H42) | I43: =SUM(I41:I42) | J43: =SUM(J41:J42) | K43: =SUM(K41:K42) | ... BK43: =SUM(BK41:BK42)
A45: Operating costs | D45: =D18+D32+D38+D43 | E45: =E18+E32+E38+E43 | F45: =F18+F32+F38+F43 | G45: =G18+G32+G38+G43 | H45: =H18+H32+H38+H43 | I45: =I18+I32+I38+I43 | J45: =J18+J32+J38+J43 | K45: =K18+K32+K38+K43 | ... BK45: =BK18+BK32+BK38+BK43

Sheet P&L
A1: Ilé: p&l
A2: Revenue by line, the four cost buckets, EBITDA. Before tax and depreciation.
A4: Month | D4: 1 | E4: 2 | F4: 3 | G4: 4 | H4: 5 | I4: 6 | J4: 7 | K4: 8 | L4: 9 | M4: 10 | N4: 11 | O4: 12 | P4: 13 | Q4: 14 | R4: 15 | S4: 16 | T4: 17 | U4: 18 | V4: 19 | W4: 20 | X4: 21 | Y4: 22 | Z4: 23 | AA4: 24 | AB4: 25 | AC4: 26 | AD4: 27 | AE4: 28 | AF4: 29 | AG4: 30 | AH4: 31 | AI4: 32 | AJ4: 33 | AK4: 34 | AL4: 35 | AM4: 36 | AN4: 37 | AO4: 38 | AP4: 39 | AQ4: 40 | AR4: 41 | AS4: 42 | AT4: 43 | AU4: 44 | AV4: 45 | AW4: 46 | AX4: 47 | AY4: 48 | AZ4: 49 | BA4: 50 | BB4: 51 | BC4: 52 | BD4: 53 | BE4: 54 | BF4: 55 | BG4: 56 | BH4: 57 | BI4: 58 | BJ4: 59 | BK4: 60
A5: Period | D5: Nov 2026 | E5: Dec 2026 | F5: Jan 2027 | G5: Feb 2027 | H5: Mar 2027 | I5: Apr 2027 | J5: May 2027 | K5: Jun 2027 | L5: Jul 2027 | M5: Aug 2027 | N5: Sep 2027 | O5: Oct 2027 | P5: Nov 2027 | Q5: Dec 2027 | R5: Jan 2028 | S5: Feb 2028 | T5: Mar 2028 | U5: Apr 2028 | V5: May 2028 | W5: Jun 2028 | X5: Jul 2028 | Y5: Aug 2028 | Z5: Sep 2028 | AA5: Oct 2028 | AB5: Nov 2028 | AC5: Dec 2028 | AD5: Jan 2029 | AE5: Feb 2029 | AF5: Mar 2029 | AG5: Apr 2029 | AH5: May 2029 | AI5: Jun 2029 | AJ5: Jul 2029 | AK5: Aug 2029 | AL5: Sep 2029 | AM5: Oct 2029 | AN5: Nov 2029 | AO5: Dec 2029 | AP5: Jan 2030 | AQ5: Feb 2030 | AR5: Mar 2030 | AS5: Apr 2030 | AT5: May 2030 | AU5: Jun 2030 | AV5: Jul 2030 | AW5: Aug 2030 | AX5: Sep 2030 | AY5: Oct 2030 | AZ5: Nov 2030 | BA5: Dec 2030 | BB5: Jan 2031 | BC5: Feb 2031 | BD5: Mar 2031 | BE5: Apr 2031 | BF5: May 2031 | BG5: Jun 2031 | BH5: Jul 2031 | BI5: Aug 2031 | BJ5: Sep 2031 | BK5: Oct 2031
A6: Model year | D6: =INT((D$4-1)/12)+1 | E6: =INT((E$4-1)/12)+1 | F6: =INT((F$4-1)/12)+1 | G6: =INT((G$4-1)/12)+1 | H6: =INT((H$4-1)/12)+1 | I6: =INT((I$4-1)/12)+1 | J6: =INT((J$4-1)/12)+1 | K6: =INT((K$4-1)/12)+1 | ... BK6: =INT((BK$4-1)/12)+1
A8: Revenue
A9: Care in the home | D9: ='Revenue'!D14 | E9: ='Revenue'!E14 | F9: ='Revenue'!F14 | G9: ='Revenue'!G14 | H9: ='Revenue'!H14 | I9: ='Revenue'!I14 | J9: ='Revenue'!J14 | K9: ='Revenue'!K14 | ... BK9: ='Revenue'!BK14
A10: Residential care | D10: ='Revenue'!D20 | E10: ='Revenue'!E20 | F10: ='Revenue'!F20 | G10: ='Revenue'!G20 | H10: ='Revenue'!H20 | I10: ='Revenue'!I20 | J10: ='Revenue'!J20 | K10: ='Revenue'!K20 | ... BK10: ='Revenue'!BK20
A11: Mortuary and pathology | D11: ='Revenue'!D26 | E11: ='Revenue'!E26 | F11: ='Revenue'!F26 | G11: ='Revenue'!G26 | H11: ='Revenue'!H26 | I11: ='Revenue'!I26 | J11: ='Revenue'!J26 | K11: ='Revenue'!K26 | ... BK11: ='Revenue'!BK26
A12: Software | D12: ='Revenue'!D30 | E12: ='Revenue'!E30 | F12: ='Revenue'!F30 | G12: ='Revenue'!G30 | H12: ='Revenue'!H30 | I12: ='Revenue'!I30 | J12: ='Revenue'!J30 | K12: ='Revenue'!K30 | ... BK12: ='Revenue'!BK30
A13: Revenue | D13: =SUM(D9:D12) | E13: =SUM(E9:E12) | F13: =SUM(F9:F12) | G13: =SUM(G9:G12) | H13: =SUM(H9:H12) | I13: =SUM(I9:I12) | J13: =SUM(J9:J12) | K13: =SUM(K9:K12) | ... BK13: =SUM(BK9:BK12)
A15: Costs
A16: Direct costs | D16: ='Costs'!D18 | E16: ='Costs'!E18 | F16: ='Costs'!F18 | G16: ='Costs'!G18 | H16: ='Costs'!H18 | I16: ='Costs'!I18 | J16: ='Costs'!J18 | K16: ='Costs'!K18 | ... BK16: ='Costs'!BK18
A17: Site operating costs | D17: ='Costs'!D32 | E17: ='Costs'!E32 | F17: ='Costs'!F32 | G17: ='Costs'!G32 | H17: ='Costs'!H32 | I17: ='Costs'!I32 | J17: ='Costs'!J32 | K17: ='Costs'!K32 | ... BK17: ='Costs'!BK32
A18: Leases | D18: ='Costs'!D38 | E18: ='Costs'!E38 | F18: ='Costs'!F38 | G18: ='Costs'!G38 | H18: ='Costs'!H38 | I18: ='Costs'!I38 | J18: ='Costs'!J38 | K18: ='Costs'!K38 | ... BK18: ='Costs'!BK38
A19: Central overhead | D19: ='Costs'!D43 | E19: ='Costs'!E43 | F19: ='Costs'!F43 | G19: ='Costs'!G43 | H19: ='Costs'!H43 | I19: ='Costs'!I43 | J19: ='Costs'!J43 | K19: ='Costs'!K43 | ... BK19: ='Costs'!BK43
A20: Operating costs | D20: =SUM(D16:D19) | E20: =SUM(E16:E19) | F20: =SUM(F16:F19) | G20: =SUM(G16:G19) | H20: =SUM(H16:H19) | I20: =SUM(I16:I19) | J20: =SUM(J16:J19) | K20: =SUM(K16:K19) | ... BK20: =SUM(BK16:BK19)
A22: Contribution after direct costs | D22: =D13-D16 | E22: =E13-E16 | F22: =F13-F16 | G22: =G13-G16 | H22: =H13-H16 | I22: =I13-I16 | J22: =J13-J16 | K22: =K13-K16 | ... BK22: =BK13-BK16
A23: EBITDA | D23: =D13-D20 | E23: =E13-E20 | F23: =F13-F20 | G23: =G13-G20 | H23: =H13-H20 | I23: =I13-I20 | J23: =J13-J20 | K23: =K13-K20 | ... BK23: =BK13-BK20
A24: EBITDA margin | D24: =IF(D13=0,0,D23/D13) | E24: =IF(E13=0,0,E23/E13) | F24: =IF(F13=0,0,F23/F13) | G24: =IF(G13=0,0,G23/G13) | H24: =IF(H13=0,0,H23/H13) | I24: =IF(I13=0,0,I23/I13) | J24: =IF(J13=0,0,J23/J13) | K24: =IF(K13=0,0,K23/K13) | ... BK24: =IF(BK13=0,0,BK23/BK13)
A25: Positive for six months running (flag) | D25: =IF(COUNTIF(D23:I23,">0")=MIN(6,60-D$4+1),IF(D23>0,1,0),0) | E25: =IF(COUNTIF(E23:J23,">0")=MIN(6,60-E$4+1),IF(E23>0,1,0),0) | F25: =IF(COUNTIF(F23:K23,">0")=MIN(6,60-F$4+1),IF(F23>0,1,0),0) | G25: =IF(COUNTIF(G23:L23,">0")=MIN(6,60-G$4+1),IF(G23>0,1,0),0) | H25: =IF(COUNTIF(H23:M23,">0")=MIN(6,60-H$4+1),IF(H23>0,1,0),0) | I25: =IF(COUNTIF(I23:N23,">0")=MIN(6,60-I$4+1),IF(I23>0,1,0),0) | J25: =IF(COUNTIF(J23:O23,">0")=MIN(6,60-J$4+1),IF(J23>0,1,0),0) | K25: =IF(COUNTIF(K23:P23,">0")=MIN(6,60-K$4+1),IF(K23>0,1,0),0) | ... BF25: =IF(COUNTIF(BF23:BK23,">0")=MIN(6,60-BF$4+1),IF(BF23>0,1,0),0) | BG25: =IF(COUNTIF(BG23:BK23,">0")=MIN(6,60-BG$4+1),IF(BG23>0,1,0),0) | BH25: =IF(COUNTIF(BH23:BK23,">0")=MIN(6,60-BH$4+1),IF(BH23>0,1,0),0) | BI25: =IF(COUNTIF(BI23:BK23,">0")=MIN(6,60-BI$4+1),IF(BI23>0,1,0),0) | BJ25: =IF(COUNTIF(BJ23:BK23,">0")=MIN(6,60-BJ$4+1),IF(BJ23>0,1,0),0) | BK25: =IF(COUNTIF(BK23:BK23,">0")=MIN(6,60-BK$4+1),IF(BK23>0,1,0),0)

Sheet Cash Flow
A1: Ilé: cash flow
A2: EBITDA to cash. Before tax. The raise arrives in month 1.
A4: Month | D4: 1 | E4: 2 | F4: 3 | G4: 4 | H4: 5 | I4: 6 | J4: 7 | K4: 8 | L4: 9 | M4: 10 | N4: 11 | O4: 12 | P4: 13 | Q4: 14 | R4: 15 | S4: 16 | T4: 17 | U4: 18 | V4: 19 | W4: 20 | X4: 21 | Y4: 22 | Z4: 23 | AA4: 24 | AB4: 25 | AC4: 26 | AD4: 27 | AE4: 28 | AF4: 29 | AG4: 30 | AH4: 31 | AI4: 32 | AJ4: 33 | AK4: 34 | AL4: 35 | AM4: 36 | AN4: 37 | AO4: 38 | AP4: 39 | AQ4: 40 | AR4: 41 | AS4: 42 | AT4: 43 | AU4: 44 | AV4: 45 | AW4: 46 | AX4: 47 | AY4: 48 | AZ4: 49 | BA4: 50 | BB4: 51 | BC4: 52 | BD4: 53 | BE4: 54 | BF4: 55 | BG4: 56 | BH4: 57 | BI4: 58 | BJ4: 59 | BK4: 60
A5: Period | D5: Nov 2026 | E5: Dec 2026 | F5: Jan 2027 | G5: Feb 2027 | H5: Mar 2027 | I5: Apr 2027 | J5: May 2027 | K5: Jun 2027 | L5: Jul 2027 | M5: Aug 2027 | N5: Sep 2027 | O5: Oct 2027 | P5: Nov 2027 | Q5: Dec 2027 | R5: Jan 2028 | S5: Feb 2028 | T5: Mar 2028 | U5: Apr 2028 | V5: May 2028 | W5: Jun 2028 | X5: Jul 2028 | Y5: Aug 2028 | Z5: Sep 2028 | AA5: Oct 2028 | AB5: Nov 2028 | AC5: Dec 2028 | AD5: Jan 2029 | AE5: Feb 2029 | AF5: Mar 2029 | AG5: Apr 2029 | AH5: May 2029 | AI5: Jun 2029 | AJ5: Jul 2029 | AK5: Aug 2029 | AL5: Sep 2029 | AM5: Oct 2029 | AN5: Nov 2029 | AO5: Dec 2029 | AP5: Jan 2030 | AQ5: Feb 2030 | AR5: Mar 2030 | AS5: Apr 2030 | AT5: May 2030 | AU5: Jun 2030 | AV5: Jul 2030 | AW5: Aug 2030 | AX5: Sep 2030 | AY5: Oct 2030 | AZ5: Nov 2030 | BA5: Dec 2030 | BB5: Jan 2031 | BC5: Feb 2031 | BD5: Mar 2031 | BE5: Apr 2031 | BF5: May 2031 | BG5: Jun 2031 | BH5: Jul 2031 | BI5: Aug 2031 | BJ5: Sep 2031 | BK5: Oct 2031
A6: Model year | D6: =INT((D$4-1)/12)+1 | E6: =INT((E$4-1)/12)+1 | F6: =INT((F$4-1)/12)+1 | G6: =INT((G$4-1)/12)+1 | H6: =INT((H$4-1)/12)+1 | I6: =INT((I$4-1)/12)+1 | J6: =INT((J$4-1)/12)+1 | K6: =INT((K$4-1)/12)+1 | ... BK6: =INT((BK$4-1)/12)+1
A8: EBITDA | D8: ='P&L'!D23 | E8: ='P&L'!E23 | F8: ='P&L'!F23 | G8: ='P&L'!G23 | H8: ='P&L'!H23 | I8: ='P&L'!I23 | J8: ='P&L'!J23 | K8: ='P&L'!K23 | ... BK8: ='P&L'!BK23
A9: Add back leases charged | D9: ='Costs'!D38 | E9: ='Costs'!E38 | F9: ='Costs'!F38 | G9: ='Costs'!G38 | H9: ='Costs'!H38 | I9: ='Costs'!I38 | J9: ='Costs'!J38 | K9: ='Costs'!K38 | ... BK9: ='Costs'!BK38
A10: Leases paid a year ahead
A11: Residence one building | D11: =-IF(AND(D$4>=RES1_EFF-LEASE_LEAD,MOD(D$4-(RES1_EFF-LEASE_LEAD),12)=0),RES_LEASE_YR,0) | E11: =-IF(AND(E$4>=RES1_EFF-LEASE_LEAD,MOD(E$4-(RES1_EFF-LEASE_LEAD),12)=0),RES_LEASE_YR,0) | F11: =-IF(AND(F$4>=RES1_EFF-LEASE_LEAD,MOD(F$4-(RES1_EFF-LEASE_LEAD),12)=0),RES_LEASE_YR,0) | G11: =-IF(AND(G$4>=RES1_EFF-LEASE_LEAD,MOD(G$4-(RES1_EFF-LEASE_LEAD),12)=0),RES_LEASE_YR,0) | H11: =-IF(AND(H$4>=RES1_EFF-LEASE_LEAD,MOD(H$4-(RES1_EFF-LEASE_LEAD),12)=0),RES_LEASE_YR,0) | I11: =-IF(AND(I$4>=RES1_EFF-LEASE_LEAD,MOD(I$4-(RES1_EFF-LEASE_LEAD),12)=0),RES_LEASE_YR,0) | J11: =-IF(AND(J$4>=RES1_EFF-LEASE_LEAD,MOD(J$4-(RES1_EFF-LEASE_LEAD),12)=0),RES_LEASE_YR,0) | K11: =-IF(AND(K$4>=RES1_EFF-LEASE_LEAD,MOD(K$4-(RES1_EFF-LEASE_LEAD),12)=0),RES_LEASE_YR,0) | ... BK11: =-IF(AND(BK$4>=RES1_EFF-LEASE_LEAD,MOD(BK$4-(RES1_EFF-LEASE_LEAD),12)=0),RES_LEASE_YR,0)
A12: Residence two building | D12: =-IF(AND(D$4>=RES2_EFF-LEASE_LEAD,MOD(D$4-(RES2_EFF-LEASE_LEAD),12)=0),RES_LEASE_YR,0) | E12: =-IF(AND(E$4>=RES2_EFF-LEASE_LEAD,MOD(E$4-(RES2_EFF-LEASE_LEAD),12)=0),RES_LEASE_YR,0) | F12: =-IF(AND(F$4>=RES2_EFF-LEASE_LEAD,MOD(F$4-(RES2_EFF-LEASE_LEAD),12)=0),RES_LEASE_YR,0) | G12: =-IF(AND(G$4>=RES2_EFF-LEASE_LEAD,MOD(G$4-(RES2_EFF-LEASE_LEAD),12)=0),RES_LEASE_YR,0) | H12: =-IF(AND(H$4>=RES2_EFF-LEASE_LEAD,MOD(H$4-(RES2_EFF-LEASE_LEAD),12)=0),RES_LEASE_YR,0) | I12: =-IF(AND(I$4>=RES2_EFF-LEASE_LEAD,MOD(I$4-(RES2_EFF-LEASE_LEAD),12)=0),RES_LEASE_YR,0) | J12: =-IF(AND(J$4>=RES2_EFF-LEASE_LEAD,MOD(J$4-(RES2_EFF-LEASE_LEAD),12)=0),RES_LEASE_YR,0) | K12: =-IF(AND(K$4>=RES2_EFF-LEASE_LEAD,MOD(K$4-(RES2_EFF-LEASE_LEAD),12)=0),RES_LEASE_YR,0) | ... BK12: =-IF(AND(BK$4>=RES2_EFF-LEASE_LEAD,MOD(BK$4-(RES2_EFF-LEASE_LEAD),12)=0),RES_LEASE_YR,0)
A13: Mortuary site | D13: =-IF(AND(D$4>=MORT_LEASE_FROM,MOD(D$4-MORT_LEASE_FROM,12)=0),MORT_LEASE_YR,0) | E13: =-IF(AND(E$4>=MORT_LEASE_FROM,MOD(E$4-MORT_LEASE_FROM,12)=0),MORT_LEASE_YR,0) | F13: =-IF(AND(F$4>=MORT_LEASE_FROM,MOD(F$4-MORT_LEASE_FROM,12)=0),MORT_LEASE_YR,0) | G13: =-IF(AND(G$4>=MORT_LEASE_FROM,MOD(G$4-MORT_LEASE_FROM,12)=0),MORT_LEASE_YR,0) | H13: =-IF(AND(H$4>=MORT_LEASE_FROM,MOD(H$4-MORT_LEASE_FROM,12)=0),MORT_LEASE_YR,0) | I13: =-IF(AND(I$4>=MORT_LEASE_FROM,MOD(I$4-MORT_LEASE_FROM,12)=0),MORT_LEASE_YR,0) | J13: =-IF(AND(J$4>=MORT_LEASE_FROM,MOD(J$4-MORT_LEASE_FROM,12)=0),MORT_LEASE_YR,0) | K13: =-IF(AND(K$4>=MORT_LEASE_FROM,MOD(K$4-MORT_LEASE_FROM,12)=0),MORT_LEASE_YR,0) | ... BK13: =-IF(AND(BK$4>=MORT_LEASE_FROM,MOD(BK$4-MORT_LEASE_FROM,12)=0),MORT_LEASE_YR,0)
A14: Leases paid | D14: =SUM(D11:D13) | E14: =SUM(E11:E13) | F14: =SUM(F11:F13) | G14: =SUM(G11:G13) | H14: =SUM(H11:H13) | I14: =SUM(I11:I13) | J14: =SUM(J11:J13) | K14: =SUM(K11:K13) | ... BK14: =SUM(BK11:BK13)
A16: Capital spend
A17: Residence one, building works | D17: =-IF(AND(D$4>=RES1_EFF-LEASE_LEAD,D$4<RES1_EFF),RES_CONV/LEASE_LEAD,0) | E17: =-IF(AND(E$4>=RES1_EFF-LEASE_LEAD,E$4<RES1_EFF),RES_CONV/LEASE_LEAD,0) | F17: =-IF(AND(F$4>=RES1_EFF-LEASE_LEAD,F$4<RES1_EFF),RES_CONV/LEASE_LEAD,0) | G17: =-IF(AND(G$4>=RES1_EFF-LEASE_LEAD,G$4<RES1_EFF),RES_CONV/LEASE_LEAD,0) | H17: =-IF(AND(H$4>=RES1_EFF-LEASE_LEAD,H$4<RES1_EFF),RES_CONV/LEASE_LEAD,0) | I17: =-IF(AND(I$4>=RES1_EFF-LEASE_LEAD,I$4<RES1_EFF),RES_CONV/LEASE_LEAD,0) | J17: =-IF(AND(J$4>=RES1_EFF-LEASE_LEAD,J$4<RES1_EFF),RES_CONV/LEASE_LEAD,0) | K17: =-IF(AND(K$4>=RES1_EFF-LEASE_LEAD,K$4<RES1_EFF),RES_CONV/LEASE_LEAD,0) | ... BK17: =-IF(AND(BK$4>=RES1_EFF-LEASE_LEAD,BK$4<RES1_EFF),RES_CONV/LEASE_LEAD,0)
A18: Residence one, equipment and pre-opening | D18: =-IF(AND(D$4>=RES1_EFF-EQUIP_MONTHS,D$4<RES1_EFF),RES_EQUIP/EQUIP_MONTHS,0) | E18: =-IF(AND(E$4>=RES1_EFF-EQUIP_MONTHS,E$4<RES1_EFF),RES_EQUIP/EQUIP_MONTHS,0) | F18: =-IF(AND(F$4>=RES1_EFF-EQUIP_MONTHS,F$4<RES1_EFF),RES_EQUIP/EQUIP_MONTHS,0) | G18: =-IF(AND(G$4>=RES1_EFF-EQUIP_MONTHS,G$4<RES1_EFF),RES_EQUIP/EQUIP_MONTHS,0) | H18: =-IF(AND(H$4>=RES1_EFF-EQUIP_MONTHS,H$4<RES1_EFF),RES_EQUIP/EQUIP_MONTHS,0) | I18: =-IF(AND(I$4>=RES1_EFF-EQUIP_MONTHS,I$4<RES1_EFF),RES_EQUIP/EQUIP_MONTHS,0) | J18: =-IF(AND(J$4>=RES1_EFF-EQUIP_MONTHS,J$4<RES1_EFF),RES_EQUIP/EQUIP_MONTHS,0) | K18: =-IF(AND(K$4>=RES1_EFF-EQUIP_MONTHS,K$4<RES1_EFF),RES_EQUIP/EQUIP_MONTHS,0) | ... BK18: =-IF(AND(BK$4>=RES1_EFF-EQUIP_MONTHS,BK$4<RES1_EFF),RES_EQUIP/EQUIP_MONTHS,0)
A19: Residence two, building works | D19: =-IF(AND(D$4>=RES2_EFF-LEASE_LEAD,D$4<RES2_EFF),RES_CONV/LEASE_LEAD,0) | E19: =-IF(AND(E$4>=RES2_EFF-LEASE_LEAD,E$4<RES2_EFF),RES_CONV/LEASE_LEAD,0) | F19: =-IF(AND(F$4>=RES2_EFF-LEASE_LEAD,F$4<RES2_EFF),RES_CONV/LEASE_LEAD,0) | G19: =-IF(AND(G$4>=RES2_EFF-LEASE_LEAD,G$4<RES2_EFF),RES_CONV/LEASE_LEAD,0) | H19: =-IF(AND(H$4>=RES2_EFF-LEASE_LEAD,H$4<RES2_EFF),RES_CONV/LEASE_LEAD,0) | I19: =-IF(AND(I$4>=RES2_EFF-LEASE_LEAD,I$4<RES2_EFF),RES_CONV/LEASE_LEAD,0) | J19: =-IF(AND(J$4>=RES2_EFF-LEASE_LEAD,J$4<RES2_EFF),RES_CONV/LEASE_LEAD,0) | K19: =-IF(AND(K$4>=RES2_EFF-LEASE_LEAD,K$4<RES2_EFF),RES_CONV/LEASE_LEAD,0) | ... BK19: =-IF(AND(BK$4>=RES2_EFF-LEASE_LEAD,BK$4<RES2_EFF),RES_CONV/LEASE_LEAD,0)
A20: Residence two, equipment and pre-opening | D20: =-IF(AND(D$4>=RES2_EFF-EQUIP_MONTHS,D$4<RES2_EFF),RES_EQUIP/EQUIP_MONTHS,0) | E20: =-IF(AND(E$4>=RES2_EFF-EQUIP_MONTHS,E$4<RES2_EFF),RES_EQUIP/EQUIP_MONTHS,0) | F20: =-IF(AND(F$4>=RES2_EFF-EQUIP_MONTHS,F$4<RES2_EFF),RES_EQUIP/EQUIP_MONTHS,0) | G20: =-IF(AND(G$4>=RES2_EFF-EQUIP_MONTHS,G$4<RES2_EFF),RES_EQUIP/EQUIP_MONTHS,0) | H20: =-IF(AND(H$4>=RES2_EFF-EQUIP_MONTHS,H$4<RES2_EFF),RES_EQUIP/EQUIP_MONTHS,0) | I20: =-IF(AND(I$4>=RES2_EFF-EQUIP_MONTHS,I$4<RES2_EFF),RES_EQUIP/EQUIP_MONTHS,0) | J20: =-IF(AND(J$4>=RES2_EFF-EQUIP_MONTHS,J$4<RES2_EFF),RES_EQUIP/EQUIP_MONTHS,0) | K20: =-IF(AND(K$4>=RES2_EFF-EQUIP_MONTHS,K$4<RES2_EFF),RES_EQUIP/EQUIP_MONTHS,0) | ... BK20: =-IF(AND(BK$4>=RES2_EFF-EQUIP_MONTHS,BK$4<RES2_EFF),RES_EQUIP/EQUIP_MONTHS,0)
A21: Mortuary build | D21: =-IF(AND(D$4>=MBUILD_M,D$4<MBUILD_M+MBUILD_N),MBUILD/MBUILD_N,0) | E21: =-IF(AND(E$4>=MBUILD_M,E$4<MBUILD_M+MBUILD_N),MBUILD/MBUILD_N,0) | F21: =-IF(AND(F$4>=MBUILD_M,F$4<MBUILD_M+MBUILD_N),MBUILD/MBUILD_N,0) | G21: =-IF(AND(G$4>=MBUILD_M,G$4<MBUILD_M+MBUILD_N),MBUILD/MBUILD_N,0) | H21: =-IF(AND(H$4>=MBUILD_M,H$4<MBUILD_M+MBUILD_N),MBUILD/MBUILD_N,0) | I21: =-IF(AND(I$4>=MBUILD_M,I$4<MBUILD_M+MBUILD_N),MBUILD/MBUILD_N,0) | J21: =-IF(AND(J$4>=MBUILD_M,J$4<MBUILD_M+MBUILD_N),MBUILD/MBUILD_N,0) | K21: =-IF(AND(K$4>=MBUILD_M,K$4<MBUILD_M+MBUILD_N),MBUILD/MBUILD_N,0) | ... BK21: =-IF(AND(BK$4>=MBUILD_M,BK$4<MBUILD_M+MBUILD_N),MBUILD/MBUILD_N,0)
A22: Autopsy suite | D22: =-IF(D$4=AUTCAP_M,AUTCAP,0) | E22: =-IF(E$4=AUTCAP_M,AUTCAP,0) | F22: =-IF(F$4=AUTCAP_M,AUTCAP,0) | G22: =-IF(G$4=AUTCAP_M,AUTCAP,0) | H22: =-IF(H$4=AUTCAP_M,AUTCAP,0) | I22: =-IF(I$4=AUTCAP_M,AUTCAP,0) | J22: =-IF(J$4=AUTCAP_M,AUTCAP,0) | K22: =-IF(K$4=AUTCAP_M,AUTCAP,0) | ... BK22: =-IF(BK$4=AUTCAP_M,AUTCAP,0)
A23: Mortuary expansion | D23: =-IF(AND(D$4>=MEXP_M,D$4<MEXP_M+MEXP_N),MEXP/MEXP_N,0) | E23: =-IF(AND(E$4>=MEXP_M,E$4<MEXP_M+MEXP_N),MEXP/MEXP_N,0) | F23: =-IF(AND(F$4>=MEXP_M,F$4<MEXP_M+MEXP_N),MEXP/MEXP_N,0) | G23: =-IF(AND(G$4>=MEXP_M,G$4<MEXP_M+MEXP_N),MEXP/MEXP_N,0) | H23: =-IF(AND(H$4>=MEXP_M,H$4<MEXP_M+MEXP_N),MEXP/MEXP_N,0) | I23: =-IF(AND(I$4>=MEXP_M,I$4<MEXP_M+MEXP_N),MEXP/MEXP_N,0) | J23: =-IF(AND(J$4>=MEXP_M,J$4<MEXP_M+MEXP_N),MEXP/MEXP_N,0) | K23: =-IF(AND(K$4>=MEXP_M,K$4<MEXP_M+MEXP_N),MEXP/MEXP_N,0) | ... BK23: =-IF(AND(BK$4>=MEXP_M,BK$4<MEXP_M+MEXP_N),MEXP/MEXP_N,0)
A24: Capital spend | D24: =SUM(D17:D23) | E24: =SUM(E17:E23) | F24: =SUM(F17:F23) | G24: =SUM(G17:G23) | H24: =SUM(H17:H23) | I24: =SUM(I17:I23) | J24: =SUM(J17:J23) | K24: =SUM(K17:K23) | ... BK24: =SUM(BK17:BK23)
A26: Residence deposits received | D26: =IF(D$4=RES1_EFF-1,DEPOSIT*DEPOSITS_N,0)+IF(D$4=RES2_EFF-1,DEPOSIT*DEPOSITS_N,0) | E26: =IF(E$4=RES1_EFF-1,DEPOSIT*DEPOSITS_N,0)+IF(E$4=RES2_EFF-1,DEPOSIT*DEPOSITS_N,0) | F26: =IF(F$4=RES1_EFF-1,DEPOSIT*DEPOSITS_N,0)+IF(F$4=RES2_EFF-1,DEPOSIT*DEPOSITS_N,0) | G26: =IF(G$4=RES1_EFF-1,DEPOSIT*DEPOSITS_N,0)+IF(G$4=RES2_EFF-1,DEPOSIT*DEPOSITS_N,0) | H26: =IF(H$4=RES1_EFF-1,DEPOSIT*DEPOSITS_N,0)+IF(H$4=RES2_EFF-1,DEPOSIT*DEPOSITS_N,0) | I26: =IF(I$4=RES1_EFF-1,DEPOSIT*DEPOSITS_N,0)+IF(I$4=RES2_EFF-1,DEPOSIT*DEPOSITS_N,0) | J26: =IF(J$4=RES1_EFF-1,DEPOSIT*DEPOSITS_N,0)+IF(J$4=RES2_EFF-1,DEPOSIT*DEPOSITS_N,0) | K26: =IF(K$4=RES1_EFF-1,DEPOSIT*DEPOSITS_N,0)+IF(K$4=RES2_EFF-1,DEPOSIT*DEPOSITS_N,0) | ... BK26: =IF(BK$4=RES1_EFF-1,DEPOSIT*DEPOSITS_N,0)+IF(BK$4=RES2_EFF-1,DEPOSIT*DEPOSITS_N,0)
A28: Net cash flow before funding | D28: =D8+D9+D14+D24+D26 | E28: =E8+E9+E14+E24+E26 | F28: =F8+F9+F14+F24+F26 | G28: =G8+G9+G14+G24+G26 | H28: =H8+H9+H14+H24+H26 | I28: =I8+I9+I14+I24+I26 | J28: =J8+J9+J14+J24+J26 | K28: =K8+K9+K14+K24+K26 | ... BK28: =BK8+BK9+BK14+BK24+BK26
A29: Cumulative cash before funding | D29: =SUM($D$28:D28) | E29: =SUM($D$28:E28) | F29: =SUM($D$28:F28) | G29: =SUM($D$28:G28) | H29: =SUM($D$28:H28) | I29: =SUM($D$28:I28) | J29: =SUM($D$28:J28) | K29: =SUM($D$28:K28) | ... BK29: =SUM($D$28:BK28)
A30: Equity raised | D30: =IF(D$4=1,RAISE_NGN,0) | E30: =IF(E$4=1,RAISE_NGN,0) | F30: =IF(F$4=1,RAISE_NGN,0) | G30: =IF(G$4=1,RAISE_NGN,0) | H30: =IF(H$4=1,RAISE_NGN,0) | I30: =IF(I$4=1,RAISE_NGN,0) | J30: =IF(J$4=1,RAISE_NGN,0) | K30: =IF(K$4=1,RAISE_NGN,0) | ... BK30: =IF(BK$4=1,RAISE_NGN,0)
A31: Cash balance | D31: =D29+SUM($D$30:D30) | E31: =E29+SUM($D$30:E30) | F31: =F29+SUM($D$30:F30) | G31: =G29+SUM($D$30:G30) | H31: =H29+SUM($D$30:H30) | I31: =I29+SUM($D$30:I30) | J31: =J29+SUM($D$30:J30) | K31: =K29+SUM($D$30:K30) | ... BK31: =BK29+SUM($D$30:BK30)
A33: Peak funding need | B33: =-MIN($D$29:$BK$29)
A34: Month cash is lowest | B34: =INDEX($D$5:$BK$5,MATCH(MIN($D$29:$BK$29),$D$29:$BK$29,0))
A35: EBITDA positive, and stays positive, from | B35: =IFERROR(INDEX($D$5:$BK$5,MATCH(1,'P&L'!$D$25:$BK$25,0)),"Not in five years")
A36: Lowest cash balance after the raise | B36: =MIN($D$31:$BK$31)

Sheet Annual
A1: Ilé: five-year summary
A2: Year one is November 2026 to October 2027. Naira, before tax. Every figure sums the monthly sheets.
B4: Year 1 | C4: Year 2 | D4: Year 3 | E4: Year 4 | F4: Year 5
A5: Period | B5: Nov 2026 to Oct 2027 | C5: Nov 2027 to Oct 2028 | D5: Nov 2028 to Oct 2029 | E5: Nov 2029 to Oct 2030 | F5: Nov 2030 to Oct 2031
A6: Revenue by stream
A7: Concierge geriatric care | B7: =SUMIF('Revenue'!$D$6:$BK$6,1,'Revenue'!$D$9:$BK$9) | C7: =SUMIF('Revenue'!$D$6:$BK$6,2,'Revenue'!$D$9:$BK$9) | D7: =SUMIF('Revenue'!$D$6:$BK$6,3,'Revenue'!$D$9:$BK$9) | E7: =SUMIF('Revenue'!$D$6:$BK$6,4,'Revenue'!$D$9:$BK$9) | F7: =SUMIF('Revenue'!$D$6:$BK$6,5,'Revenue'!$D$9:$BK$9)
A8: Care at home | B8: =SUMIF('Revenue'!$D$6:$BK$6,1,'Revenue'!$D$10:$BK$10) | C8: =SUMIF('Revenue'!$D$6:$BK$6,2,'Revenue'!$D$10:$BK$10) | D8: =SUMIF('Revenue'!$D$6:$BK$6,3,'Revenue'!$D$10:$BK$10) | E8: =SUMIF('Revenue'!$D$6:$BK$6,4,'Revenue'!$D$10:$BK$10) | F8: =SUMIF('Revenue'!$D$6:$BK$6,5,'Revenue'!$D$10:$BK$10)
A9: Virtual consultations | B9: =SUMIF('Revenue'!$D$6:$BK$6,1,'Revenue'!$D$11:$BK$11) | C9: =SUMIF('Revenue'!$D$6:$BK$6,2,'Revenue'!$D$11:$BK$11) | D9: =SUMIF('Revenue'!$D$6:$BK$6,3,'Revenue'!$D$11:$BK$11) | E9: =SUMIF('Revenue'!$D$6:$BK$6,4,'Revenue'!$D$11:$BK$11) | F9: =SUMIF('Revenue'!$D$6:$BK$6,5,'Revenue'!$D$11:$BK$11)
A10: Post-operative rehabilitation | B10: =SUMIF('Revenue'!$D$6:$BK$6,1,'Revenue'!$D$12:$BK$12) | C10: =SUMIF('Revenue'!$D$6:$BK$6,2,'Revenue'!$D$12:$BK$12) | D10: =SUMIF('Revenue'!$D$6:$BK$6,3,'Revenue'!$D$12:$BK$12) | E10: =SUMIF('Revenue'!$D$6:$BK$6,4,'Revenue'!$D$12:$BK$12) | F10: =SUMIF('Revenue'!$D$6:$BK$6,5,'Revenue'!$D$12:$BK$12)
A11: Palliative care at home | B11: =SUMIF('Revenue'!$D$6:$BK$6,1,'Revenue'!$D$13:$BK$13) | C11: =SUMIF('Revenue'!$D$6:$BK$6,2,'Revenue'!$D$13:$BK$13) | D11: =SUMIF('Revenue'!$D$6:$BK$6,3,'Revenue'!$D$13:$BK$13) | E11: =SUMIF('Revenue'!$D$6:$BK$6,4,'Revenue'!$D$13:$BK$13) | F11: =SUMIF('Revenue'!$D$6:$BK$6,5,'Revenue'!$D$13:$BK$13)
A12: Residence, long-stay | B12: =SUMIF('Revenue'!$D$6:$BK$6,1,'Revenue'!$D$17:$BK$17) | C12: =SUMIF('Revenue'!$D$6:$BK$6,2,'Revenue'!$D$17:$BK$17) | D12: =SUMIF('Revenue'!$D$6:$BK$6,3,'Revenue'!$D$17:$BK$17) | E12: =SUMIF('Revenue'!$D$6:$BK$6,4,'Revenue'!$D$17:$BK$17) | F12: =SUMIF('Revenue'!$D$6:$BK$6,5,'Revenue'!$D$17:$BK$17)
A13: Step-down beds | B13: =SUMIF('Revenue'!$D$6:$BK$6,1,'Revenue'!$D$18:$BK$18) | C13: =SUMIF('Revenue'!$D$6:$BK$6,2,'Revenue'!$D$18:$BK$18) | D13: =SUMIF('Revenue'!$D$6:$BK$6,3,'Revenue'!$D$18:$BK$18) | E13: =SUMIF('Revenue'!$D$6:$BK$6,4,'Revenue'!$D$18:$BK$18) | F13: =SUMIF('Revenue'!$D$6:$BK$6,5,'Revenue'!$D$18:$BK$18)
A14: Palliative wing | B14: =SUMIF('Revenue'!$D$6:$BK$6,1,'Revenue'!$D$19:$BK$19) | C14: =SUMIF('Revenue'!$D$6:$BK$6,2,'Revenue'!$D$19:$BK$19) | D14: =SUMIF('Revenue'!$D$6:$BK$6,3,'Revenue'!$D$19:$BK$19) | E14: =SUMIF('Revenue'!$D$6:$BK$6,4,'Revenue'!$D$19:$BK$19) | F14: =SUMIF('Revenue'!$D$6:$BK$6,5,'Revenue'!$D$19:$BK$19)
A15: Mortuary preservation | B15: =SUMIF('Revenue'!$D$6:$BK$6,1,'Revenue'!$D$23:$BK$23) | C15: =SUMIF('Revenue'!$D$6:$BK$6,2,'Revenue'!$D$23:$BK$23) | D15: =SUMIF('Revenue'!$D$6:$BK$6,3,'Revenue'!$D$23:$BK$23) | E15: =SUMIF('Revenue'!$D$6:$BK$6,4,'Revenue'!$D$23:$BK$23) | F15: =SUMIF('Revenue'!$D$6:$BK$6,5,'Revenue'!$D$23:$BK$23)
A16: Preparation and repatriation | B16: =SUMIF('Revenue'!$D$6:$BK$6,1,'Revenue'!$D$24:$BK$24) | C16: =SUMIF('Revenue'!$D$6:$BK$6,2,'Revenue'!$D$24:$BK$24) | D16: =SUMIF('Revenue'!$D$6:$BK$6,3,'Revenue'!$D$24:$BK$24) | E16: =SUMIF('Revenue'!$D$6:$BK$6,4,'Revenue'!$D$24:$BK$24) | F16: =SUMIF('Revenue'!$D$6:$BK$6,5,'Revenue'!$D$24:$BK$24)
A17: Autopsy and pathology | B17: =SUMIF('Revenue'!$D$6:$BK$6,1,'Revenue'!$D$25:$BK$25) | C17: =SUMIF('Revenue'!$D$6:$BK$6,2,'Revenue'!$D$25:$BK$25) | D17: =SUMIF('Revenue'!$D$6:$BK$6,3,'Revenue'!$D$25:$BK$25) | E17: =SUMIF('Revenue'!$D$6:$BK$6,4,'Revenue'!$D$25:$BK$25) | F17: =SUMIF('Revenue'!$D$6:$BK$6,5,'Revenue'!$D$25:$BK$25)
A18: Software licences | B18: =SUMIF('Revenue'!$D$6:$BK$6,1,'Revenue'!$D$29:$BK$29) | C18: =SUMIF('Revenue'!$D$6:$BK$6,2,'Revenue'!$D$29:$BK$29) | D18: =SUMIF('Revenue'!$D$6:$BK$6,3,'Revenue'!$D$29:$BK$29) | E18: =SUMIF('Revenue'!$D$6:$BK$6,4,'Revenue'!$D$29:$BK$29) | F18: =SUMIF('Revenue'!$D$6:$BK$6,5,'Revenue'!$D$29:$BK$29)
A19: Revenue by business line
A20: Care in the home | B20: =SUMIF('Revenue'!$D$6:$BK$6,1,'Revenue'!$D$14:$BK$14) | C20: =SUMIF('Revenue'!$D$6:$BK$6,2,'Revenue'!$D$14:$BK$14) | D20: =SUMIF('Revenue'!$D$6:$BK$6,3,'Revenue'!$D$14:$BK$14) | E20: =SUMIF('Revenue'!$D$6:$BK$6,4,'Revenue'!$D$14:$BK$14) | F20: =SUMIF('Revenue'!$D$6:$BK$6,5,'Revenue'!$D$14:$BK$14)
A21: Residential care | B21: =SUMIF('Revenue'!$D$6:$BK$6,1,'Revenue'!$D$20:$BK$20) | C21: =SUMIF('Revenue'!$D$6:$BK$6,2,'Revenue'!$D$20:$BK$20) | D21: =SUMIF('Revenue'!$D$6:$BK$6,3,'Revenue'!$D$20:$BK$20) | E21: =SUMIF('Revenue'!$D$6:$BK$6,4,'Revenue'!$D$20:$BK$20) | F21: =SUMIF('Revenue'!$D$6:$BK$6,5,'Revenue'!$D$20:$BK$20)
A22: Mortuary and pathology | B22: =SUMIF('Revenue'!$D$6:$BK$6,1,'Revenue'!$D$26:$BK$26) | C22: =SUMIF('Revenue'!$D$6:$BK$6,2,'Revenue'!$D$26:$BK$26) | D22: =SUMIF('Revenue'!$D$6:$BK$6,3,'Revenue'!$D$26:$BK$26) | E22: =SUMIF('Revenue'!$D$6:$BK$6,4,'Revenue'!$D$26:$BK$26) | F22: =SUMIF('Revenue'!$D$6:$BK$6,5,'Revenue'!$D$26:$BK$26)
A23: Software | B23: =SUMIF('Revenue'!$D$6:$BK$6,1,'Revenue'!$D$30:$BK$30) | C23: =SUMIF('Revenue'!$D$6:$BK$6,2,'Revenue'!$D$30:$BK$30) | D23: =SUMIF('Revenue'!$D$6:$BK$6,3,'Revenue'!$D$30:$BK$30) | E23: =SUMIF('Revenue'!$D$6:$BK$6,4,'Revenue'!$D$30:$BK$30) | F23: =SUMIF('Revenue'!$D$6:$BK$6,5,'Revenue'!$D$30:$BK$30)
A24: Revenue | B24: =SUMIF('Revenue'!$D$6:$BK$6,1,'Revenue'!$D$32:$BK$32) | C24: =SUMIF('Revenue'!$D$6:$BK$6,2,'Revenue'!$D$32:$BK$32) | D24: =SUMIF('Revenue'!$D$6:$BK$6,3,'Revenue'!$D$32:$BK$32) | E24: =SUMIF('Revenue'!$D$6:$BK$6,4,'Revenue'!$D$32:$BK$32) | F24: =SUMIF('Revenue'!$D$6:$BK$6,5,'Revenue'!$D$32:$BK$32)
A25: Costs
A26: Direct costs | B26: =SUMIF('Costs'!$D$6:$BK$6,1,'Costs'!$D$18:$BK$18) | C26: =SUMIF('Costs'!$D$6:$BK$6,2,'Costs'!$D$18:$BK$18) | D26: =SUMIF('Costs'!$D$6:$BK$6,3,'Costs'!$D$18:$BK$18) | E26: =SUMIF('Costs'!$D$6:$BK$6,4,'Costs'!$D$18:$BK$18) | F26: =SUMIF('Costs'!$D$6:$BK$6,5,'Costs'!$D$18:$BK$18)
A27: Site operating costs | B27: =SUMIF('Costs'!$D$6:$BK$6,1,'Costs'!$D$32:$BK$32) | C27: =SUMIF('Costs'!$D$6:$BK$6,2,'Costs'!$D$32:$BK$32) | D27: =SUMIF('Costs'!$D$6:$BK$6,3,'Costs'!$D$32:$BK$32) | E27: =SUMIF('Costs'!$D$6:$BK$6,4,'Costs'!$D$32:$BK$32) | F27: =SUMIF('Costs'!$D$6:$BK$6,5,'Costs'!$D$32:$BK$32)
A28: Leases | B28: =SUMIF('Costs'!$D$6:$BK$6,1,'Costs'!$D$38:$BK$38) | C28: =SUMIF('Costs'!$D$6:$BK$6,2,'Costs'!$D$38:$BK$38) | D28: =SUMIF('Costs'!$D$6:$BK$6,3,'Costs'!$D$38:$BK$38) | E28: =SUMIF('Costs'!$D$6:$BK$6,4,'Costs'!$D$38:$BK$38) | F28: =SUMIF('Costs'!$D$6:$BK$6,5,'Costs'!$D$38:$BK$38)
A29: Central overhead | B29: =SUMIF('Costs'!$D$6:$BK$6,1,'Costs'!$D$43:$BK$43) | C29: =SUMIF('Costs'!$D$6:$BK$6,2,'Costs'!$D$43:$BK$43) | D29: =SUMIF('Costs'!$D$6:$BK$6,3,'Costs'!$D$43:$BK$43) | E29: =SUMIF('Costs'!$D$6:$BK$6,4,'Costs'!$D$43:$BK$43) | F29: =SUMIF('Costs'!$D$6:$BK$6,5,'Costs'!$D$43:$BK$43)
A30: EBITDA | B30: =SUMIF('P&L'!$D$6:$BK$6,1,'P&L'!$D$23:$BK$23) | C30: =SUMIF('P&L'!$D$6:$BK$6,2,'P&L'!$D$23:$BK$23) | D30: =SUMIF('P&L'!$D$6:$BK$6,3,'P&L'!$D$23:$BK$23) | E30: =SUMIF('P&L'!$D$6:$BK$6,4,'P&L'!$D$23:$BK$23) | F30: =SUMIF('P&L'!$D$6:$BK$6,5,'P&L'!$D$23:$BK$23)
A31: EBITDA margin | B31: =IF(B24=0,0,B30/B24) | C31: =IF(C24=0,0,C30/C24) | D31: =IF(D24=0,0,D30/D24) | E31: =IF(E24=0,0,E30/E24) | F31: =IF(F24=0,0,F30/F24)
A32: Cash
A33: Leases paid | B33: =SUMIF('Cash Flow'!$D$6:$BK$6,1,'Cash Flow'!$D$14:$BK$14) | C33: =SUMIF('Cash Flow'!$D$6:$BK$6,2,'Cash Flow'!$D$14:$BK$14) | D33: =SUMIF('Cash Flow'!$D$6:$BK$6,3,'Cash Flow'!$D$14:$BK$14) | E33: =SUMIF('Cash Flow'!$D$6:$BK$6,4,'Cash Flow'!$D$14:$BK$14) | F33: =SUMIF('Cash Flow'!$D$6:$BK$6,5,'Cash Flow'!$D$14:$BK$14)
A34: Capital spend | B34: =SUMIF('Cash Flow'!$D$6:$BK$6,1,'Cash Flow'!$D$24:$BK$24) | C34: =SUMIF('Cash Flow'!$D$6:$BK$6,2,'Cash Flow'!$D$24:$BK$24) | D34: =SUMIF('Cash Flow'!$D$6:$BK$6,3,'Cash Flow'!$D$24:$BK$24) | E34: =SUMIF('Cash Flow'!$D$6:$BK$6,4,'Cash Flow'!$D$24:$BK$24) | F34: =SUMIF('Cash Flow'!$D$6:$BK$6,5,'Cash Flow'!$D$24:$BK$24)
A35: Deposits received | B35: =SUMIF('Cash Flow'!$D$6:$BK$6,1,'Cash Flow'!$D$26:$BK$26) | C35: =SUMIF('Cash Flow'!$D$6:$BK$6,2,'Cash Flow'!$D$26:$BK$26) | D35: =SUMIF('Cash Flow'!$D$6:$BK$6,3,'Cash Flow'!$D$26:$BK$26) | E35: =SUMIF('Cash Flow'!$D$6:$BK$6,4,'Cash Flow'!$D$26:$BK$26) | F35: =SUMIF('Cash Flow'!$D$6:$BK$6,5,'Cash Flow'!$D$26:$BK$26)
A36: Net cash flow before funding | B36: =SUMIF('Cash Flow'!$D$6:$BK$6,1,'Cash Flow'!$D$28:$BK$28) | C36: =SUMIF('Cash Flow'!$D$6:$BK$6,2,'Cash Flow'!$D$28:$BK$28) | D36: =SUMIF('Cash Flow'!$D$6:$BK$6,3,'Cash Flow'!$D$28:$BK$28) | E36: =SUMIF('Cash Flow'!$D$6:$BK$6,4,'Cash Flow'!$D$28:$BK$28) | F36: =SUMIF('Cash Flow'!$D$6:$BK$6,5,'Cash Flow'!$D$28:$BK$28)
A37: Cumulative cash before funding, year end | B37: =INDEX('Cash Flow'!$D$29:$BK$29,12) | C37: =INDEX('Cash Flow'!$D$29:$BK$29,24) | D37: =INDEX('Cash Flow'!$D$29:$BK$29,36) | E37: =INDEX('Cash Flow'!$D$29:$BK$29,48) | F37: =INDEX('Cash Flow'!$D$29:$BK$29,60)
A38: Cash balance after the raise, year end | B38: =INDEX('Cash Flow'!$D$31:$BK$31,12) | C38: =INDEX('Cash Flow'!$D$31:$BK$31,24) | D38: =INDEX('Cash Flow'!$D$31:$BK$31,36) | E38: =INDEX('Cash Flow'!$D$31:$BK$31,48) | F38: =INDEX('Cash Flow'!$D$31:$BK$31,60)
A40: Year-end operating measures
A41: Care at home clients | B41: =INDEX('Volumes'!$D$9:$BK$9,12) | C41: =INDEX('Volumes'!$D$9:$BK$9,24) | D41: =INDEX('Volumes'!$D$9:$BK$9,36) | E41: =INDEX('Volumes'!$D$9:$BK$9,48) | F41: =INDEX('Volumes'!$D$9:$BK$9,60)
A42: Concierge members | B42: =INDEX('Volumes'!$D$10:$BK$10,12) | C42: =INDEX('Volumes'!$D$10:$BK$10,24) | D42: =INDEX('Volumes'!$D$10:$BK$10,36) | E42: =INDEX('Volumes'!$D$10:$BK$10,48) | F42: =INDEX('Volumes'!$D$10:$BK$10,60)
A43: Occupied beds, both residences | B43: =INDEX('Volumes'!$D$22:$BK$22,12) | C43: =INDEX('Volumes'!$D$22:$BK$22,24) | D43: =INDEX('Volumes'!$D$22:$BK$22,36) | E43: =INDEX('Volumes'!$D$22:$BK$22,48) | F43: =INDEX('Volumes'!$D$22:$BK$22,60)
A44: Bodies held on an average day | B44: =INDEX('Volumes'!$D$26:$BK$26,12) | C44: =INDEX('Volumes'!$D$26:$BK$26,24) | D44: =INDEX('Volumes'!$D$26:$BK$26,36) | E44: =INDEX('Volumes'!$D$26:$BK$26,48) | F44: =INDEX('Volumes'!$D$26:$BK$26,60)
A45: Organisations licensing | B45: =INDEX('Volumes'!$D$32:$BK$32,12) | C45: =INDEX('Volumes'!$D$32:$BK$32,24) | D45: =INDEX('Volumes'!$D$32:$BK$32,36) | E45: =INDEX('Volumes'!$D$32:$BK$32,48) | F45: =INDEX('Volumes'!$D$32:$BK$32,60)

Sheet Unit Economics
A1: Ilé: unit economics at steady state
A2: Per unit a month, from the assumptions.
A4: Stream | B4: Revenue a month | C4: Direct cost | D4: Contribution | E4: Margin
A5: Concierge, per member | B5: =CONC_FEE | C5: =CONC_FEE*CONC_DIRECT | D5: =B5-C5 | E5: =IF(B5=0,0,D5/B5)
A6: Care at home, per client | B6: =HOME_ARPU | C6: =HOME_ARPU*HOME_DIRECT | D6: =B6-C6 | E6: =IF(B6=0,0,D6/B6)
A7: Rehabilitation, per six-week package | B7: =REHAB_FEE | C7: =REHAB_FEE*REHAB_DIRECT | D7: =B7-C7 | E7: =IF(B7=0,0,D7/B7)
A8: Palliative at home, per patient | B8: =PALLH_FEE | C8: =PALLH_FEE*PALLH_DIRECT | D8: =B8-C8 | E8: =IF(B8=0,0,D8/B8)
A9: Virtual consultation, each | B9: =CONS_FEE | C9: =CONS_FEE*CONS_DIRECT | D9: =B9-C9 | E9: =IF(B9=0,0,D9/B9)
A10: Software, per organisation | B10: =SAAS_FEE | C10: =SAAS_FEE*SAAS_DIRECT | D10: =B10-C10 | E10: =IF(B10=0,0,D10/B10)
A11: Residence at ceiling, a month | B11: =RES_CAP*RES_FEE+STEP_CAP*DAYS_PM*STEP_DAY+PALL_CAP*PALL_FEE | C11: =RES_STAFF+(RES_CAP+STEP_CAP+PALL_CAP)*RES_PER_BED+RES_UTIL+RES_OTHER+RES_LEASE_YR/12 | D11: =B11-C11 | E11: =IF(B11=0,0,D11/B11)
A12: Mortuary at 80 places, a month | B12: =MORT_CAP2*MORT_FILL*DAYS_PM*MORT_DAY+MORT_CAP2*MORT_FILL*DAYS_PM/MORT_STAY*MORT_CASE+REPAT_V3*REPAT_FEE+AUT_V3*AUT_FEE | C12: =MSTAFF_V2+MPOWER_V2+MORT_OTHER+MORT_LEASE_YR/12+MORT_CAP2*MORT_FILL*DAYS_PM/MORT_STAY*MORT_CASE_COST+REPAT_V3*REPAT_FEE*REPAT_DIRECT+AUT_V3*AUT_FEE*AUT_DIRECT | D12: =B12-C12 | E12: =IF(B12=0,0,D12/B12)
A14: Residence and mortuary rows are site EBITDA: they include staffing, running costs and the lease.

Sheet Market
A1: Ilé: Lagos market at premium prices
A2: Bottom up, with checks against mature markets.
A4: Lagos aged 60 and over | B4: =LAGOS_POP*SHARE_60
A5: Of them dependent in daily living | B5: =B4*ADL_DEP
A6: Deaths a year in Lagos | B6: =LAGOS_POP*DEATH_RATE
A7: Care in the home | B7: =B5*PREMIUM*HOME_ARPU*12 | C7: Premium dependent elders at the care at home price
A8: Residential care | B8: =B5*NEEDS_24H*PREMIUM*RES_FEE*12 | C8: Those needing round-the-clock care
A9: Palliative care | B9: =B6*PALL_NEED*PREMIUM*PALL_MONTHS*PALL_FEE
A10: Mortuary | B10: =B6*PRIVATE_MORT*(MORT_STAY*MORT_DAY+MORT_CASE)
A11: Lagos premium market a year | B11: =SUM(B7:B10)
A12: Ilé year-five revenue as a share | B12: =IF(B11=0,0,Y5_REV/B11)
A13: Check: residents at the England care-home rate (2.5% of 65+) | B13: =B4*PREMIUM*0.025 | C13: ONS 2021
A14: Check: palliative families at the US hospice rate (51.7%) | B14: =B6*PREMIUM*0.517 | C14: MedPAC 2023

Sheet Returns
A1: Ilé: the round and returns
A2: Equity value at exit = year-five EBITDA x multiple + cash on hand.
A4: Raise | B4: =RAISE_USD
A5: Stake | B5: =STAKE
A6: Pre-money | B6: =PRE_USD
A7: Post-money | B7: =POST_USD
A8: Year-five EBITDA, naira | B8: =Y5_EBITDA
A9: Cash on hand at month 60, naira | B9: =INDEX('Cash Flow'!$D$31:$BK$31,60)
A11: Exit multiple | B11: Equity value ($) | C11: Investor's stake ($) | D11: Multiple on raise | E11: Weak naira equity ($)
A12: =EXIT_LO | B12: =(A12*$B$8+$B$9)/FX | C12: =B12*STAKE | D12: =C12/RAISE_USD | E12: =(A12*$B$8+$B$9)/FX_WEAK
A13: =EXIT_MID | B13: =(A13*$B$8+$B$9)/FX | C13: =B13*STAKE | D13: =C13/RAISE_USD | E13: =(A13*$B$8+$B$9)/FX_WEAK
A14: =EXIT_HI | B14: =(A14*$B$8+$B$9)/FX | C14: =B14*STAKE | D14: =C14/RAISE_USD | E14: =(A14*$B$8+$B$9)/FX_WEAK
A16: Before any later dilution. Software valued at the care multiple, not a software multiple.

Sheet Scenarios
A1: Ilé: stress cases
A2: Recorded from the model. The first four rows can be reproduced with the yellow levers on Assumptions; the live result is below.
A4: Case | B4: Peak funding (₦) | C4: Low point | D4: Year-5 EBITDA (₦)
A5: Base case | B5: 676971268 | C5: Dec 2027 | D5: 993282775
A6: Residence fills at half speed | B6: 698790805 | C6: Jul 2028 | D6: 946579275
A7: Mortuary fills at half speed | B7: 713795699 | C7: Jul 2028 | D7: 809361038
A8: Residence one opens six months late | B8: 606580713 | C8: Jun 2028 | D8: 924309775
A9: Care at home reaches half the clients by month 18 | B9: 734222305 | C9: Jul 2028 | D9: 985362775
A10: Concierge membership at half the target | B10: 717351305 | C10: Jul 2028 | D10: 885220275
A11: No software licences sold | B11: 680837174 | C11: Jul 2028 | D11: 921314025
A12: Residence and mortuary both at half speed | B12: 738460199 | C12: Jul 2028 | D12: 682879038
A14: Levers: Residence fill speed 0.5; Mortuary fill speed 0.5; Residence delay 6; Software licences sold 0.
A16: Live, at the current levers
A17: Peak funding need | B17: =PEAK
A18: Raise in naira | B18: =RAISE_NGN
A19: Headroom | B19: =RAISE_NGN-PEAK
A20: Year-five EBITDA | B20: =Y5_EBITDA
